{
  "zoneID": 216,
  "entities": [
    {
      "name": "none",
      "serverID": 0,
      "targetIndex": 0,
      "zoneID": 0
    },
    {
      "name": "Brine Crab",
      "serverID": 17661953,
      "targetIndex": 1,
      "zoneID": 216
    },
    {
      "name": "Brine Crab",
      "serverID": 17661954,
      "targetIndex": 2,
      "zoneID": 216
    },
    {
      "name": "Brine Crab",
      "serverID": 17661955,
      "targetIndex": 3,
      "zoneID": 216
    },
    {
      "name": "Brine Crab",
      "serverID": 17661956,
      "targetIndex": 4,
      "zoneID": 216
    },
    {
      "name": "Brine Crab",
      "serverID": 17661957,
      "targetIndex": 5,
      "zoneID": 216
    },
    {
      "name": "Crabtrap",
      "serverID": 17661958,
      "targetIndex": 6,
      "zoneID": 216
    },
    {
      "name": "Crabtrap",
      "serverID": 17661959,
      "targetIndex": 7,
      "zoneID": 216
    },
    {
      "name": "Crabtrap",
      "serverID": 17661960,
      "targetIndex": 8,
      "zoneID": 216
    },
    {
      "name": "Crabtrap",
      "serverID": 17661961,
      "targetIndex": 9,
      "zoneID": 216
    },
    {
      "name": "Crabtrap",
      "serverID": 17661962,
      "targetIndex": 10,
      "zoneID": 216
    },
    {
      "name": "Protoamoeban",
      "serverID": 17661963,
      "targetIndex": 11,
      "zoneID": 216
    },
    {
      "name": "Protoamoeban",
      "serverID": 17661964,
      "targetIndex": 12,
      "zoneID": 216
    },
    {
      "name": "Protoamoeban",
      "serverID": 17661965,
      "targetIndex": 13,
      "zoneID": 216
    },
    {
      "name": "Protoamoeban",
      "serverID": 17661966,
      "targetIndex": 14,
      "zoneID": 216
    },
    {
      "name": "Protoamoeban",
      "serverID": 17661967,
      "targetIndex": 15,
      "zoneID": 216
    },
    {
      "name": "Protoamoeban",
      "serverID": 17661968,
      "targetIndex": 16,
      "zoneID": 216
    },
    {
      "name": "Protoamoeban",
      "serverID": 17661969,
      "targetIndex": 17,
      "zoneID": 216
    },
    {
      "name": "Protoamoeban",
      "serverID": 17661970,
      "targetIndex": 18,
      "zoneID": 216
    },
    {
      "name": "Protoamoeban",
      "serverID": 17661971,
      "targetIndex": 19,
      "zoneID": 216
    },
    {
      "name": "Protoamoeban",
      "serverID": 17661972,
      "targetIndex": 20,
      "zoneID": 216
    },
    {
      "name": "Protoamoeban",
      "serverID": 17661973,
      "targetIndex": 21,
      "zoneID": 216
    },
    {
      "name": "Protoamoeban",
      "serverID": 17661974,
      "targetIndex": 22,
      "zoneID": 216
    },
    {
      "name": "Protoamoeban",
      "serverID": 17661975,
      "targetIndex": 23,
      "zoneID": 216
    },
    {
      "name": "Protoamoeban",
      "serverID": 17661976,
      "targetIndex": 24,
      "zoneID": 216
    },
    {
      "name": "Protoamoeban",
      "serverID": 17661977,
      "targetIndex": 25,
      "zoneID": 216
    },
    {
      "name": "Protoamoeban",
      "serverID": 17661978,
      "targetIndex": 26,
      "zoneID": 216
    },
    {
      "name": "Protoamoeban",
      "serverID": 17661979,
      "targetIndex": 27,
      "zoneID": 216
    },
    {
      "name": "Protoamoeban",
      "serverID": 17661980,
      "targetIndex": 28,
      "zoneID": 216
    },
    {
      "name": "Protoamoeban",
      "serverID": 17661981,
      "targetIndex": 29,
      "zoneID": 216
    },
    {
      "name": "Protoamoeban",
      "serverID": 17661982,
      "targetIndex": 30,
      "zoneID": 216
    },
    {
      "name": "Ephemeral Amoeban",
      "serverID": 17661983,
      "targetIndex": 31,
      "zoneID": 216
    },
    {
      "name": "Escarp Murex",
      "serverID": 17661984,
      "targetIndex": 32,
      "zoneID": 216
    },
    {
      "name": "Escarp Murex",
      "serverID": 17661985,
      "targetIndex": 33,
      "zoneID": 216
    },
    {
      "name": "Escarp Murex",
      "serverID": 17661986,
      "targetIndex": 34,
      "zoneID": 216
    },
    {
      "name": "Escarp Murex",
      "serverID": 17661987,
      "targetIndex": 35,
      "zoneID": 216
    },
    {
      "name": "Escarp Murex",
      "serverID": 17661988,
      "targetIndex": 36,
      "zoneID": 216
    },
    {
      "name": "Escarp Murex",
      "serverID": 17661989,
      "targetIndex": 37,
      "zoneID": 216
    },
    {
      "name": "Escarp Murex",
      "serverID": 17661990,
      "targetIndex": 38,
      "zoneID": 216
    },
    {
      "name": "Escarp Murex",
      "serverID": 17661991,
      "targetIndex": 39,
      "zoneID": 216
    },
    {
      "name": "Escarp Murex",
      "serverID": 17661992,
      "targetIndex": 40,
      "zoneID": 216
    },
    {
      "name": "Escarp Murex",
      "serverID": 17661993,
      "targetIndex": 41,
      "zoneID": 216
    },
    {
      "name": "Escarp Murex",
      "serverID": 17661994,
      "targetIndex": 42,
      "zoneID": 216
    },
    {
      "name": "Escarp Murex",
      "serverID": 17661995,
      "targetIndex": 43,
      "zoneID": 216
    },
    {
      "name": "Escarp Murex",
      "serverID": 17661996,
      "targetIndex": 44,
      "zoneID": 216
    },
    {
      "name": "Escarp Murex",
      "serverID": 17661997,
      "targetIndex": 45,
      "zoneID": 216
    },
    {
      "name": "Escarp Murex",
      "serverID": 17661998,
      "targetIndex": 46,
      "zoneID": 216
    },
    {
      "name": "Escarp Murex",
      "serverID": 17661999,
      "targetIndex": 47,
      "zoneID": 216
    },
    {
      "name": "Escarp Murex",
      "serverID": 17662000,
      "targetIndex": 48,
      "zoneID": 216
    },
    {
      "name": "Escarp Murex",
      "serverID": 17662001,
      "targetIndex": 49,
      "zoneID": 216
    },
    {
      "name": "Escarp Murex",
      "serverID": 17662002,
      "targetIndex": 50,
      "zoneID": 216
    },
    {
      "name": "Escarp Murex",
      "serverID": 17662003,
      "targetIndex": 51,
      "zoneID": 216
    },
    {
      "name": "Escarp Murex",
      "serverID": 17662004,
      "targetIndex": 52,
      "zoneID": 216
    },
    {
      "name": "Ephemeral Murex",
      "serverID": 17662005,
      "targetIndex": 53,
      "zoneID": 216
    },
    {
      "name": "Limestone Hare",
      "serverID": 17662006,
      "targetIndex": 54,
      "zoneID": 216
    },
    {
      "name": "Limestone Hare",
      "serverID": 17662007,
      "targetIndex": 55,
      "zoneID": 216
    },
    {
      "name": "Limestone Hare",
      "serverID": 17662008,
      "targetIndex": 56,
      "zoneID": 216
    },
    {
      "name": "Limestone Hare",
      "serverID": 17662009,
      "targetIndex": 57,
      "zoneID": 216
    },
    {
      "name": "Limestone Hare",
      "serverID": 17662010,
      "targetIndex": 58,
      "zoneID": 216
    },
    {
      "name": "Limestone Hare",
      "serverID": 17662011,
      "targetIndex": 59,
      "zoneID": 216
    },
    {
      "name": "Limestone Hare",
      "serverID": 17662012,
      "targetIndex": 60,
      "zoneID": 216
    },
    {
      "name": "Limestone Hare",
      "serverID": 17662013,
      "targetIndex": 61,
      "zoneID": 216
    },
    {
      "name": "Limestone Hare",
      "serverID": 17662014,
      "targetIndex": 62,
      "zoneID": 216
    },
    {
      "name": "Limestone Hare",
      "serverID": 17662015,
      "targetIndex": 63,
      "zoneID": 216
    },
    {
      "name": "Limestone Hare",
      "serverID": 17662016,
      "targetIndex": 64,
      "zoneID": 216
    },
    {
      "name": "Limestone Hare",
      "serverID": 17662017,
      "targetIndex": 65,
      "zoneID": 216
    },
    {
      "name": "Limestone Hare",
      "serverID": 17662018,
      "targetIndex": 66,
      "zoneID": 216
    },
    {
      "name": "Limestone Hare",
      "serverID": 17662019,
      "targetIndex": 67,
      "zoneID": 216
    },
    {
      "name": "Limestone Hare",
      "serverID": 17662020,
      "targetIndex": 68,
      "zoneID": 216
    },
    {
      "name": "Limestone Hare",
      "serverID": 17662021,
      "targetIndex": 69,
      "zoneID": 216
    },
    {
      "name": "Limestone Hare",
      "serverID": 17662022,
      "targetIndex": 70,
      "zoneID": 216
    },
    {
      "name": "Ephemeral Amoeban",
      "serverID": 17662023,
      "targetIndex": 71,
      "zoneID": 216
    },
    {
      "name": "Shore Spider",
      "serverID": 17662024,
      "targetIndex": 72,
      "zoneID": 216
    },
    {
      "name": "Shore Spider",
      "serverID": 17662025,
      "targetIndex": 73,
      "zoneID": 216
    },
    {
      "name": "Shore Spider",
      "serverID": 17662026,
      "targetIndex": 74,
      "zoneID": 216
    },
    {
      "name": "Shore Spider",
      "serverID": 17662027,
      "targetIndex": 75,
      "zoneID": 216
    },
    {
      "name": "Shore Spider",
      "serverID": 17662028,
      "targetIndex": 76,
      "zoneID": 216
    },
    {
      "name": "Shore Spider",
      "serverID": 17662029,
      "targetIndex": 77,
      "zoneID": 216
    },
    {
      "name": "Shore Spider",
      "serverID": 17662030,
      "targetIndex": 78,
      "zoneID": 216
    },
    {
      "name": "Shore Spider",
      "serverID": 17662031,
      "targetIndex": 79,
      "zoneID": 216
    },
    {
      "name": "Shore Spider",
      "serverID": 17662032,
      "targetIndex": 80,
      "zoneID": 216
    },
    {
      "name": "Shore Spider",
      "serverID": 17662033,
      "targetIndex": 81,
      "zoneID": 216
    },
    {
      "name": "Shore Spider",
      "serverID": 17662034,
      "targetIndex": 82,
      "zoneID": 216
    },
    {
      "name": "Shore Spider",
      "serverID": 17662035,
      "targetIndex": 83,
      "zoneID": 216
    },
    {
      "name": "Shore Spider",
      "serverID": 17662036,
      "targetIndex": 84,
      "zoneID": 216
    },
    {
      "name": "Shore Spider",
      "serverID": 17662037,
      "targetIndex": 85,
      "zoneID": 216
    },
    {
      "name": "Shore Spider",
      "serverID": 17662038,
      "targetIndex": 86,
      "zoneID": 216
    },
    {
      "name": "Ephemeral Murex",
      "serverID": 17662039,
      "targetIndex": 87,
      "zoneID": 216
    },
    {
      "name": "Overking Apkallu",
      "serverID": 17662040,
      "targetIndex": 88,
      "zoneID": 216
    },
    {
      "name": "Overking Apkallu",
      "serverID": 17662041,
      "targetIndex": 89,
      "zoneID": 216
    },
    {
      "name": "Overking Apkallu",
      "serverID": 17662042,
      "targetIndex": 90,
      "zoneID": 216
    },
    {
      "name": "Overking Apkallu",
      "serverID": 17662043,
      "targetIndex": 91,
      "zoneID": 216
    },
    {
      "name": "Overking Apkallu",
      "serverID": 17662044,
      "targetIndex": 92,
      "zoneID": 216
    },
    {
      "name": "Overking Apkallu",
      "serverID": 17662045,
      "targetIndex": 93,
      "zoneID": 216
    },
    {
      "name": "Overking Apkallu",
      "serverID": 17662046,
      "targetIndex": 94,
      "zoneID": 216
    },
    {
      "name": "Overking Apkallu",
      "serverID": 17662047,
      "targetIndex": 95,
      "zoneID": 216
    },
    {
      "name": "Overking Apkallu",
      "serverID": 17662048,
      "targetIndex": 96,
      "zoneID": 216
    },
    {
      "name": "Overking Apkallu",
      "serverID": 17662049,
      "targetIndex": 97,
      "zoneID": 216
    },
    {
      "name": "Overking Apkallu",
      "serverID": 17662050,
      "targetIndex": 98,
      "zoneID": 216
    },
    {
      "name": "Overking Apkallu",
      "serverID": 17662051,
      "targetIndex": 99,
      "zoneID": 216
    },
    {
      "name": "Overking Apkallu",
      "serverID": 17662052,
      "targetIndex": 100,
      "zoneID": 216
    },
    {
      "name": "Overking Apkallu",
      "serverID": 17662053,
      "targetIndex": 101,
      "zoneID": 216
    },
    {
      "name": "Overking Apkallu",
      "serverID": 17662054,
      "targetIndex": 102,
      "zoneID": 216
    },
    {
      "name": "Overking Apkallu",
      "serverID": 17662055,
      "targetIndex": 103,
      "zoneID": 216
    },
    {
      "name": "Overking Apkallu",
      "serverID": 17662056,
      "targetIndex": 104,
      "zoneID": 216
    },
    {
      "name": "Overking Apkallu",
      "serverID": 17662057,
      "targetIndex": 105,
      "zoneID": 216
    },
    {
      "name": "Overking Apkallu",
      "serverID": 17662058,
      "targetIndex": 106,
      "zoneID": 216
    },
    {
      "name": "Overking Apkallu",
      "serverID": 17662059,
      "targetIndex": 107,
      "zoneID": 216
    },
    {
      "name": "Overking Apkallu",
      "serverID": 17662060,
      "targetIndex": 108,
      "zoneID": 216
    },
    {
      "name": "Overking Apkallu",
      "serverID": 17662061,
      "targetIndex": 109,
      "zoneID": 216
    },
    {
      "name": "Overking Apkallu",
      "serverID": 17662062,
      "targetIndex": 110,
      "zoneID": 216
    },
    {
      "name": "Ephemeral Amoeban",
      "serverID": 17662063,
      "targetIndex": 111,
      "zoneID": 216
    },
    {
      "name": "Squib",
      "serverID": 17662064,
      "targetIndex": 112,
      "zoneID": 216
    },
    {
      "name": "Squib",
      "serverID": 17662065,
      "targetIndex": 113,
      "zoneID": 216
    },
    {
      "name": "Squib",
      "serverID": 17662066,
      "targetIndex": 114,
      "zoneID": 216
    },
    {
      "name": "Squib",
      "serverID": 17662067,
      "targetIndex": 115,
      "zoneID": 216
    },
    {
      "name": "Squib",
      "serverID": 17662068,
      "targetIndex": 116,
      "zoneID": 216
    },
    {
      "name": "Squib",
      "serverID": 17662069,
      "targetIndex": 117,
      "zoneID": 216
    },
    {
      "name": "Squib",
      "serverID": 17662070,
      "targetIndex": 118,
      "zoneID": 216
    },
    {
      "name": "Squib",
      "serverID": 17662071,
      "targetIndex": 119,
      "zoneID": 216
    },
    {
      "name": "Squib",
      "serverID": 17662072,
      "targetIndex": 120,
      "zoneID": 216
    },
    {
      "name": "Squib",
      "serverID": 17662073,
      "targetIndex": 121,
      "zoneID": 216
    },
    {
      "name": "Squib",
      "serverID": 17662074,
      "targetIndex": 122,
      "zoneID": 216
    },
    {
      "name": "Squib",
      "serverID": 17662075,
      "targetIndex": 123,
      "zoneID": 216
    },
    {
      "name": "Squib",
      "serverID": 17662076,
      "targetIndex": 124,
      "zoneID": 216
    },
    {
      "name": "Squib",
      "serverID": 17662077,
      "targetIndex": 125,
      "zoneID": 216
    },
    {
      "name": "Squib",
      "serverID": 17662078,
      "targetIndex": 126,
      "zoneID": 216
    },
    {
      "name": "Squib",
      "serverID": 17662079,
      "targetIndex": 127,
      "zoneID": 216
    },
    {
      "name": "Squib",
      "serverID": 17662080,
      "targetIndex": 128,
      "zoneID": 216
    },
    {
      "name": "Squib",
      "serverID": 17662081,
      "targetIndex": 129,
      "zoneID": 216
    },
    {
      "name": "Squib",
      "serverID": 17662082,
      "targetIndex": 130,
      "zoneID": 216
    },
    {
      "name": "Squib",
      "serverID": 17662083,
      "targetIndex": 131,
      "zoneID": 216
    },
    {
      "name": "Squib",
      "serverID": 17662084,
      "targetIndex": 132,
      "zoneID": 216
    },
    {
      "name": "Ephemeral Murex",
      "serverID": 17662085,
      "targetIndex": 133,
      "zoneID": 216
    },
    {
      "name": "Protoamoeban",
      "serverID": 17662086,
      "targetIndex": 134,
      "zoneID": 216
    },
    {
      "name": "Protoamoeban",
      "serverID": 17662087,
      "targetIndex": 135,
      "zoneID": 216
    },
    {
      "name": "Protoamoeban",
      "serverID": 17662088,
      "targetIndex": 136,
      "zoneID": 216
    },
    {
      "name": "Protoamoeban",
      "serverID": 17662089,
      "targetIndex": 137,
      "zoneID": 216
    },
    {
      "name": "Protoamoeban",
      "serverID": 17662090,
      "targetIndex": 138,
      "zoneID": 216
    },
    {
      "name": "Protoamoeban",
      "serverID": 17662091,
      "targetIndex": 139,
      "zoneID": 216
    },
    {
      "name": "Protoamoeban",
      "serverID": 17662092,
      "targetIndex": 140,
      "zoneID": 216
    },
    {
      "name": "Protoamoeban",
      "serverID": 17662093,
      "targetIndex": 141,
      "zoneID": 216
    },
    {
      "name": "Protoamoeban",
      "serverID": 17662094,
      "targetIndex": 142,
      "zoneID": 216
    },
    {
      "name": "Protoamoeban",
      "serverID": 17662095,
      "targetIndex": 143,
      "zoneID": 216
    },
    {
      "name": "Protoamoeban",
      "serverID": 17662096,
      "targetIndex": 144,
      "zoneID": 216
    },
    {
      "name": "Protoamoeban",
      "serverID": 17662097,
      "targetIndex": 145,
      "zoneID": 216
    },
    {
      "name": "Protoamoeban",
      "serverID": 17662098,
      "targetIndex": 146,
      "zoneID": 216
    },
    {
      "name": "Protoamoeban",
      "serverID": 17662099,
      "targetIndex": 147,
      "zoneID": 216
    },
    {
      "name": "Protoamoeban",
      "serverID": 17662100,
      "targetIndex": 148,
      "zoneID": 216
    },
    {
      "name": "Protoamoeban",
      "serverID": 17662101,
      "targetIndex": 149,
      "zoneID": 216
    },
    {
      "name": "Protoamoeban",
      "serverID": 17662102,
      "targetIndex": 150,
      "zoneID": 216
    },
    {
      "name": "Protoamoeban",
      "serverID": 17662103,
      "targetIndex": 151,
      "zoneID": 216
    },
    {
      "name": "Ephemeral Amoeban",
      "serverID": 17662104,
      "targetIndex": 152,
      "zoneID": 216
    },
    {
      "name": "Escarp Murex",
      "serverID": 17662105,
      "targetIndex": 153,
      "zoneID": 216
    },
    {
      "name": "Escarp Murex",
      "serverID": 17662106,
      "targetIndex": 154,
      "zoneID": 216
    },
    {
      "name": "Escarp Murex",
      "serverID": 17662107,
      "targetIndex": 155,
      "zoneID": 216
    },
    {
      "name": "Escarp Murex",
      "serverID": 17662108,
      "targetIndex": 156,
      "zoneID": 216
    },
    {
      "name": "Escarp Murex",
      "serverID": 17662109,
      "targetIndex": 157,
      "zoneID": 216
    },
    {
      "name": "Escarp Murex",
      "serverID": 17662110,
      "targetIndex": 158,
      "zoneID": 216
    },
    {
      "name": "Escarp Murex",
      "serverID": 17662111,
      "targetIndex": 159,
      "zoneID": 216
    },
    {
      "name": "Escarp Murex",
      "serverID": 17662112,
      "targetIndex": 160,
      "zoneID": 216
    },
    {
      "name": "Escarp Murex",
      "serverID": 17662113,
      "targetIndex": 161,
      "zoneID": 216
    },
    {
      "name": "Escarp Murex",
      "serverID": 17662114,
      "targetIndex": 162,
      "zoneID": 216
    },
    {
      "name": "Escarp Murex",
      "serverID": 17662115,
      "targetIndex": 163,
      "zoneID": 216
    },
    {
      "name": "Escarp Murex",
      "serverID": 17662116,
      "targetIndex": 164,
      "zoneID": 216
    },
    {
      "name": "Escarp Murex",
      "serverID": 17662117,
      "targetIndex": 165,
      "zoneID": 216
    },
    {
      "name": "Escarp Murex",
      "serverID": 17662118,
      "targetIndex": 166,
      "zoneID": 216
    },
    {
      "name": "Escarp Murex",
      "serverID": 17662119,
      "targetIndex": 167,
      "zoneID": 216
    },
    {
      "name": "Escarp Murex",
      "serverID": 17662120,
      "targetIndex": 168,
      "zoneID": 216
    },
    {
      "name": "Escarp Murex",
      "serverID": 17662121,
      "targetIndex": 169,
      "zoneID": 216
    },
    {
      "name": "Ephemeral Murex",
      "serverID": 17662122,
      "targetIndex": 170,
      "zoneID": 216
    },
    {
      "name": "Buzzfly",
      "serverID": 17662123,
      "targetIndex": 171,
      "zoneID": 216
    },
    {
      "name": "Buzzfly",
      "serverID": 17662124,
      "targetIndex": 172,
      "zoneID": 216
    },
    {
      "name": "Buzzfly",
      "serverID": 17662125,
      "targetIndex": 173,
      "zoneID": 216
    },
    {
      "name": "Buzzfly",
      "serverID": 17662126,
      "targetIndex": 174,
      "zoneID": 216
    },
    {
      "name": "Buzzfly",
      "serverID": 17662127,
      "targetIndex": 175,
      "zoneID": 216
    },
    {
      "name": "Buzzfly",
      "serverID": 17662128,
      "targetIndex": 176,
      "zoneID": 216
    },
    {
      "name": "Buzzfly",
      "serverID": 17662129,
      "targetIndex": 177,
      "zoneID": 216
    },
    {
      "name": "Buzzfly",
      "serverID": 17662130,
      "targetIndex": 178,
      "zoneID": 216
    },
    {
      "name": "Buzzfly",
      "serverID": 17662131,
      "targetIndex": 179,
      "zoneID": 216
    },
    {
      "name": "Buzzfly",
      "serverID": 17662132,
      "targetIndex": 180,
      "zoneID": 216
    },
    {
      "name": "Buzzfly",
      "serverID": 17662133,
      "targetIndex": 181,
      "zoneID": 216
    },
    {
      "name": "Buzzfly",
      "serverID": 17662134,
      "targetIndex": 182,
      "zoneID": 216
    },
    {
      "name": "Buzzfly",
      "serverID": 17662135,
      "targetIndex": 183,
      "zoneID": 216
    },
    {
      "name": "Buzzfly",
      "serverID": 17662136,
      "targetIndex": 184,
      "zoneID": 216
    },
    {
      "name": "Buzzfly",
      "serverID": 17662137,
      "targetIndex": 185,
      "zoneID": 216
    },
    {
      "name": "Buzzfly",
      "serverID": 17662138,
      "targetIndex": 186,
      "zoneID": 216
    },
    {
      "name": "Buzzfly",
      "serverID": 17662139,
      "targetIndex": 187,
      "zoneID": 216
    },
    {
      "name": "Buzzfly",
      "serverID": 17662140,
      "targetIndex": 188,
      "zoneID": 216
    },
    {
      "name": "Buzzfly",
      "serverID": 17662141,
      "targetIndex": 189,
      "zoneID": 216
    },
    {
      "name": "Buzzfly",
      "serverID": 17662142,
      "targetIndex": 190,
      "zoneID": 216
    },
    {
      "name": "Buzzfly",
      "serverID": 17662143,
      "targetIndex": 191,
      "zoneID": 216
    },
    {
      "name": "Ephemeral Amoeban",
      "serverID": 17662144,
      "targetIndex": 192,
      "zoneID": 216
    },
    {
      "name": "Gasher",
      "serverID": 17662145,
      "targetIndex": 193,
      "zoneID": 216
    },
    {
      "name": "Gasher",
      "serverID": 17662146,
      "targetIndex": 194,
      "zoneID": 216
    },
    {
      "name": "Gasher",
      "serverID": 17662147,
      "targetIndex": 195,
      "zoneID": 216
    },
    {
      "name": "Gasher",
      "serverID": 17662148,
      "targetIndex": 196,
      "zoneID": 216
    },
    {
      "name": "Gasher",
      "serverID": 17662149,
      "targetIndex": 197,
      "zoneID": 216
    },
    {
      "name": "Gasher",
      "serverID": 17662150,
      "targetIndex": 198,
      "zoneID": 216
    },
    {
      "name": "Gasher",
      "serverID": 17662151,
      "targetIndex": 199,
      "zoneID": 216
    },
    {
      "name": "Gasher",
      "serverID": 17662152,
      "targetIndex": 200,
      "zoneID": 216
    },
    {
      "name": "Gasher",
      "serverID": 17662153,
      "targetIndex": 201,
      "zoneID": 216
    },
    {
      "name": "Gasher",
      "serverID": 17662154,
      "targetIndex": 202,
      "zoneID": 216
    },
    {
      "name": "Gasher",
      "serverID": 17662155,
      "targetIndex": 203,
      "zoneID": 216
    },
    {
      "name": "Gasher",
      "serverID": 17662156,
      "targetIndex": 204,
      "zoneID": 216
    },
    {
      "name": "Gasher",
      "serverID": 17662157,
      "targetIndex": 205,
      "zoneID": 216
    },
    {
      "name": "Gasher",
      "serverID": 17662158,
      "targetIndex": 206,
      "zoneID": 216
    },
    {
      "name": "Gasher",
      "serverID": 17662159,
      "targetIndex": 207,
      "zoneID": 216
    },
    {
      "name": "Gasher",
      "serverID": 17662160,
      "targetIndex": 208,
      "zoneID": 216
    },
    {
      "name": "Ephemeral Murex",
      "serverID": 17662161,
      "targetIndex": 209,
      "zoneID": 216
    },
    {
      "name": "Slasher",
      "serverID": 17662162,
      "targetIndex": 210,
      "zoneID": 216
    },
    {
      "name": "Slasher",
      "serverID": 17662163,
      "targetIndex": 211,
      "zoneID": 216
    },
    {
      "name": "Slasher",
      "serverID": 17662164,
      "targetIndex": 212,
      "zoneID": 216
    },
    {
      "name": "Slasher",
      "serverID": 17662165,
      "targetIndex": 213,
      "zoneID": 216
    },
    {
      "name": "Slasher",
      "serverID": 17662166,
      "targetIndex": 214,
      "zoneID": 216
    },
    {
      "name": "Slasher",
      "serverID": 17662167,
      "targetIndex": 215,
      "zoneID": 216
    },
    {
      "name": "Slasher",
      "serverID": 17662168,
      "targetIndex": 216,
      "zoneID": 216
    },
    {
      "name": "Slasher",
      "serverID": 17662169,
      "targetIndex": 217,
      "zoneID": 216
    },
    {
      "name": "Slasher",
      "serverID": 17662170,
      "targetIndex": 218,
      "zoneID": 216
    },
    {
      "name": "Slasher",
      "serverID": 17662171,
      "targetIndex": 219,
      "zoneID": 216
    },
    {
      "name": "Slasher",
      "serverID": 17662172,
      "targetIndex": 220,
      "zoneID": 216
    },
    {
      "name": "Slasher",
      "serverID": 17662173,
      "targetIndex": 221,
      "zoneID": 216
    },
    {
      "name": "Slasher",
      "serverID": 17662174,
      "targetIndex": 222,
      "zoneID": 216
    },
    {
      "name": "Slasher",
      "serverID": 17662175,
      "targetIndex": 223,
      "zoneID": 216
    },
    {
      "name": "Slasher",
      "serverID": 17662176,
      "targetIndex": 224,
      "zoneID": 216
    },
    {
      "name": "Slasher",
      "serverID": 17662177,
      "targetIndex": 225,
      "zoneID": 216
    },
    {
      "name": "Slasher",
      "serverID": 17662178,
      "targetIndex": 226,
      "zoneID": 216
    },
    {
      "name": "Slasher",
      "serverID": 17662179,
      "targetIndex": 227,
      "zoneID": 216
    },
    {
      "name": "Slasher",
      "serverID": 17662180,
      "targetIndex": 228,
      "zoneID": 216
    },
    {
      "name": "Slasher",
      "serverID": 17662181,
      "targetIndex": 229,
      "zoneID": 216
    },
    {
      "name": "Ephemeral Amoeban",
      "serverID": 17662182,
      "targetIndex": 230,
      "zoneID": 216
    },
    {
      "name": "Boartrap",
      "serverID": 17662183,
      "targetIndex": 231,
      "zoneID": 216
    },
    {
      "name": "Boartrap",
      "serverID": 17662184,
      "targetIndex": 232,
      "zoneID": 216
    },
    {
      "name": "Boartrap",
      "serverID": 17662185,
      "targetIndex": 233,
      "zoneID": 216
    },
    {
      "name": "Boartrap",
      "serverID": 17662186,
      "targetIndex": 234,
      "zoneID": 216
    },
    {
      "name": "Boartrap",
      "serverID": 17662187,
      "targetIndex": 235,
      "zoneID": 216
    },
    {
      "name": "Boartrap",
      "serverID": 17662188,
      "targetIndex": 236,
      "zoneID": 216
    },
    {
      "name": "Boartrap",
      "serverID": 17662189,
      "targetIndex": 237,
      "zoneID": 216
    },
    {
      "name": "Boartrap",
      "serverID": 17662190,
      "targetIndex": 238,
      "zoneID": 216
    },
    {
      "name": "Boartrap",
      "serverID": 17662191,
      "targetIndex": 239,
      "zoneID": 216
    },
    {
      "name": "Boartrap",
      "serverID": 17662192,
      "targetIndex": 240,
      "zoneID": 216
    },
    {
      "name": "Boartrap",
      "serverID": 17662193,
      "targetIndex": 241,
      "zoneID": 216
    },
    {
      "name": "Boartrap",
      "serverID": 17662194,
      "targetIndex": 242,
      "zoneID": 216
    },
    {
      "name": "Boartrap",
      "serverID": 17662195,
      "targetIndex": 243,
      "zoneID": 216
    },
    {
      "name": "Boartrap",
      "serverID": 17662196,
      "targetIndex": 244,
      "zoneID": 216
    },
    {
      "name": "Boartrap",
      "serverID": 17662197,
      "targetIndex": 245,
      "zoneID": 216
    },
    {
      "name": "Boartrap",
      "serverID": 17662198,
      "targetIndex": 246,
      "zoneID": 216
    },
    {
      "name": "Boartrap",
      "serverID": 17662199,
      "targetIndex": 247,
      "zoneID": 216
    },
    {
      "name": "Ephemeral Murex",
      "serverID": 17662200,
      "targetIndex": 248,
      "zoneID": 216
    },
    {
      "name": "Ancient Orobon",
      "serverID": 17662201,
      "targetIndex": 249,
      "zoneID": 216
    },
    {
      "name": "Ancient Orobon",
      "serverID": 17662202,
      "targetIndex": 250,
      "zoneID": 216
    },
    {
      "name": "Ancient Orobon",
      "serverID": 17662203,
      "targetIndex": 251,
      "zoneID": 216
    },
    {
      "name": "Ancient Orobon",
      "serverID": 17662204,
      "targetIndex": 252,
      "zoneID": 216
    },
    {
      "name": "Ancient Orobon",
      "serverID": 17662205,
      "targetIndex": 253,
      "zoneID": 216
    },
    {
      "name": "Ancient Orobon",
      "serverID": 17662206,
      "targetIndex": 254,
      "zoneID": 216
    },
    {
      "name": "Ancient Orobon",
      "serverID": 17662207,
      "targetIndex": 255,
      "zoneID": 216
    },
    {
      "name": "Ancient Orobon",
      "serverID": 17662208,
      "targetIndex": 256,
      "zoneID": 216
    },
    {
      "name": "Ancient Orobon",
      "serverID": 17662209,
      "targetIndex": 257,
      "zoneID": 216
    },
    {
      "name": "Ancient Orobon",
      "serverID": 17662210,
      "targetIndex": 258,
      "zoneID": 216
    },
    {
      "name": "Ancient Orobon",
      "serverID": 17662211,
      "targetIndex": 259,
      "zoneID": 216
    },
    {
      "name": "Ancient Orobon",
      "serverID": 17662212,
      "targetIndex": 260,
      "zoneID": 216
    },
    {
      "name": "Ancient Orobon",
      "serverID": 17662213,
      "targetIndex": 261,
      "zoneID": 216
    },
    {
      "name": "Ancient Orobon",
      "serverID": 17662214,
      "targetIndex": 262,
      "zoneID": 216
    },
    {
      "name": "Ancient Orobon",
      "serverID": 17662215,
      "targetIndex": 263,
      "zoneID": 216
    },
    {
      "name": "Ephemeral Amoeban",
      "serverID": 17662216,
      "targetIndex": 264,
      "zoneID": 216
    },
    {
      "name": "Coastal Colibri",
      "serverID": 17662217,
      "targetIndex": 265,
      "zoneID": 216
    },
    {
      "name": "Coastal Colibri",
      "serverID": 17662218,
      "targetIndex": 266,
      "zoneID": 216
    },
    {
      "name": "Coastal Colibri",
      "serverID": 17662219,
      "targetIndex": 267,
      "zoneID": 216
    },
    {
      "name": "Coastal Colibri",
      "serverID": 17662220,
      "targetIndex": 268,
      "zoneID": 216
    },
    {
      "name": "Coastal Colibri",
      "serverID": 17662221,
      "targetIndex": 269,
      "zoneID": 216
    },
    {
      "name": "Coastal Colibri",
      "serverID": 17662222,
      "targetIndex": 270,
      "zoneID": 216
    },
    {
      "name": "Coastal Colibri",
      "serverID": 17662223,
      "targetIndex": 271,
      "zoneID": 216
    },
    {
      "name": "Coastal Colibri",
      "serverID": 17662224,
      "targetIndex": 272,
      "zoneID": 216
    },
    {
      "name": "Coastal Colibri",
      "serverID": 17662225,
      "targetIndex": 273,
      "zoneID": 216
    },
    {
      "name": "Coastal Colibri",
      "serverID": 17662226,
      "targetIndex": 274,
      "zoneID": 216
    },
    {
      "name": "Coastal Colibri",
      "serverID": 17662227,
      "targetIndex": 275,
      "zoneID": 216
    },
    {
      "name": "Coastal Colibri",
      "serverID": 17662228,
      "targetIndex": 276,
      "zoneID": 216
    },
    {
      "name": "Coastal Colibri",
      "serverID": 17662229,
      "targetIndex": 277,
      "zoneID": 216
    },
    {
      "name": "Coastal Colibri",
      "serverID": 17662230,
      "targetIndex": 278,
      "zoneID": 216
    },
    {
      "name": "Coastal Colibri",
      "serverID": 17662231,
      "targetIndex": 279,
      "zoneID": 216
    },
    {
      "name": "Coastal Colibri",
      "serverID": 17662232,
      "targetIndex": 280,
      "zoneID": 216
    },
    {
      "name": "Coastal Colibri",
      "serverID": 17662233,
      "targetIndex": 281,
      "zoneID": 216
    },
    {
      "name": "Coastal Colibri",
      "serverID": 17662234,
      "targetIndex": 282,
      "zoneID": 216
    },
    {
      "name": "Coastal Colibri",
      "serverID": 17662235,
      "targetIndex": 283,
      "zoneID": 216
    },
    {
      "name": "Coastal Colibri",
      "serverID": 17662236,
      "targetIndex": 284,
      "zoneID": 216
    },
    {
      "name": "Coastal Colibri",
      "serverID": 17662237,
      "targetIndex": 285,
      "zoneID": 216
    },
    {
      "name": "Coastal Colibri",
      "serverID": 17662238,
      "targetIndex": 286,
      "zoneID": 216
    },
    {
      "name": "Coastal Colibri",
      "serverID": 17662239,
      "targetIndex": 287,
      "zoneID": 216
    },
    {
      "name": "Ephemeral Murex",
      "serverID": 17662240,
      "targetIndex": 288,
      "zoneID": 216
    },
    {
      "name": "Frigatebird",
      "serverID": 17662241,
      "targetIndex": 289,
      "zoneID": 216
    },
    {
      "name": "Frigatebird",
      "serverID": 17662242,
      "targetIndex": 290,
      "zoneID": 216
    },
    {
      "name": "Frigatebird",
      "serverID": 17662243,
      "targetIndex": 291,
      "zoneID": 216
    },
    {
      "name": "Frigatebird",
      "serverID": 17662244,
      "targetIndex": 292,
      "zoneID": 216
    },
    {
      "name": "Frigatebird",
      "serverID": 17662245,
      "targetIndex": 293,
      "zoneID": 216
    },
    {
      "name": "Frigatebird",
      "serverID": 17662246,
      "targetIndex": 294,
      "zoneID": 216
    },
    {
      "name": "Frigatebird",
      "serverID": 17662247,
      "targetIndex": 295,
      "zoneID": 216
    },
    {
      "name": "Frigatebird",
      "serverID": 17662248,
      "targetIndex": 296,
      "zoneID": 216
    },
    {
      "name": "Frigatebird",
      "serverID": 17662249,
      "targetIndex": 297,
      "zoneID": 216
    },
    {
      "name": "Frigatebird",
      "serverID": 17662250,
      "targetIndex": 298,
      "zoneID": 216
    },
    {
      "name": "Frigatebird",
      "serverID": 17662251,
      "targetIndex": 299,
      "zoneID": 216
    },
    {
      "name": "Frigatebird",
      "serverID": 17662252,
      "targetIndex": 300,
      "zoneID": 216
    },
    {
      "name": "Frigatebird",
      "serverID": 17662253,
      "targetIndex": 301,
      "zoneID": 216
    },
    {
      "name": "Frigatebird",
      "serverID": 17662254,
      "targetIndex": 302,
      "zoneID": 216
    },
    {
      "name": "Frigatebird",
      "serverID": 17662255,
      "targetIndex": 303,
      "zoneID": 216
    },
    {
      "name": "Frigatebird",
      "serverID": 17662256,
      "targetIndex": 304,
      "zoneID": 216
    },
    {
      "name": "Frigatebird",
      "serverID": 17662257,
      "targetIndex": 305,
      "zoneID": 216
    },
    {
      "name": "Frigatebird",
      "serverID": 17662258,
      "targetIndex": 306,
      "zoneID": 216
    },
    {
      "name": "Frigatebird",
      "serverID": 17662259,
      "targetIndex": 307,
      "zoneID": 216
    },
    {
      "name": "Frigatebird",
      "serverID": 17662260,
      "targetIndex": 308,
      "zoneID": 216
    },
    {
      "name": "Frigatebird",
      "serverID": 17662261,
      "targetIndex": 309,
      "zoneID": 216
    },
    {
      "name": "Frigatebird",
      "serverID": 17662262,
      "targetIndex": 310,
      "zoneID": 216
    },
    {
      "name": "Ephemeral Amoeban",
      "serverID": 17662263,
      "targetIndex": 311,
      "zoneID": 216
    },
    {
      "name": "Gore Bats",
      "serverID": 17662264,
      "targetIndex": 312,
      "zoneID": 216
    },
    {
      "name": "Gore Bats",
      "serverID": 17662265,
      "targetIndex": 313,
      "zoneID": 216
    },
    {
      "name": "Gore Bats",
      "serverID": 17662266,
      "targetIndex": 314,
      "zoneID": 216
    },
    {
      "name": "Gore Bats",
      "serverID": 17662267,
      "targetIndex": 315,
      "zoneID": 216
    },
    {
      "name": "Gore Bats",
      "serverID": 17662268,
      "targetIndex": 316,
      "zoneID": 216
    },
    {
      "name": "Gore Bats",
      "serverID": 17662269,
      "targetIndex": 317,
      "zoneID": 216
    },
    {
      "name": "Gore Bats",
      "serverID": 17662270,
      "targetIndex": 318,
      "zoneID": 216
    },
    {
      "name": "Gore Bats",
      "serverID": 17662271,
      "targetIndex": 319,
      "zoneID": 216
    },
    {
      "name": "Gore Bats",
      "serverID": 17662272,
      "targetIndex": 320,
      "zoneID": 216
    },
    {
      "name": "Gore Bats",
      "serverID": 17662273,
      "targetIndex": 321,
      "zoneID": 216
    },
    {
      "name": "Gore Bats",
      "serverID": 17662274,
      "targetIndex": 322,
      "zoneID": 216
    },
    {
      "name": "Gore Bats",
      "serverID": 17662275,
      "targetIndex": 323,
      "zoneID": 216
    },
    {
      "name": "Gore Bats",
      "serverID": 17662276,
      "targetIndex": 324,
      "zoneID": 216
    },
    {
      "name": "Gore Bats",
      "serverID": 17662277,
      "targetIndex": 325,
      "zoneID": 216
    },
    {
      "name": "Gore Bats",
      "serverID": 17662278,
      "targetIndex": 326,
      "zoneID": 216
    },
    {
      "name": "Gore Bats",
      "serverID": 17662279,
      "targetIndex": 327,
      "zoneID": 216
    },
    {
      "name": "Gore Bats",
      "serverID": 17662280,
      "targetIndex": 328,
      "zoneID": 216
    },
    {
      "name": "Gore Bats",
      "serverID": 17662281,
      "targetIndex": 329,
      "zoneID": 216
    },
    {
      "name": "Gore Bats",
      "serverID": 17662282,
      "targetIndex": 330,
      "zoneID": 216
    },
    {
      "name": "Gore Bats",
      "serverID": 17662283,
      "targetIndex": 331,
      "zoneID": 216
    },
    {
      "name": "Gore Bats",
      "serverID": 17662284,
      "targetIndex": 332,
      "zoneID": 216
    },
    {
      "name": "Gore Bats",
      "serverID": 17662285,
      "targetIndex": 333,
      "zoneID": 216
    },
    {
      "name": "Gore Bats",
      "serverID": 17662286,
      "targetIndex": 334,
      "zoneID": 216
    },
    {
      "name": "Ephemeral Murex",
      "serverID": 17662287,
      "targetIndex": 335,
      "zoneID": 216
    },
    {
      "name": "Observer",
      "serverID": 17662288,
      "targetIndex": 336,
      "zoneID": 216
    },
    {
      "name": "Observer",
      "serverID": 17662289,
      "targetIndex": 337,
      "zoneID": 216
    },
    {
      "name": "Observer",
      "serverID": 17662290,
      "targetIndex": 338,
      "zoneID": 216
    },
    {
      "name": "Observer",
      "serverID": 17662291,
      "targetIndex": 339,
      "zoneID": 216
    },
    {
      "name": "Observer",
      "serverID": 17662292,
      "targetIndex": 340,
      "zoneID": 216
    },
    {
      "name": "Observer",
      "serverID": 17662293,
      "targetIndex": 341,
      "zoneID": 216
    },
    {
      "name": "Observer",
      "serverID": 17662294,
      "targetIndex": 342,
      "zoneID": 216
    },
    {
      "name": "Observer",
      "serverID": 17662295,
      "targetIndex": 343,
      "zoneID": 216
    },
    {
      "name": "Observer",
      "serverID": 17662296,
      "targetIndex": 344,
      "zoneID": 216
    },
    {
      "name": "Observer",
      "serverID": 17662297,
      "targetIndex": 345,
      "zoneID": 216
    },
    {
      "name": "Observer",
      "serverID": 17662298,
      "targetIndex": 346,
      "zoneID": 216
    },
    {
      "name": "Observer",
      "serverID": 17662299,
      "targetIndex": 347,
      "zoneID": 216
    },
    {
      "name": "Observer",
      "serverID": 17662300,
      "targetIndex": 348,
      "zoneID": 216
    },
    {
      "name": "Observer",
      "serverID": 17662301,
      "targetIndex": 349,
      "zoneID": 216
    },
    {
      "name": "Observer",
      "serverID": 17662302,
      "targetIndex": 350,
      "zoneID": 216
    },
    {
      "name": "Observer",
      "serverID": 17662303,
      "targetIndex": 351,
      "zoneID": 216
    },
    {
      "name": "Observer",
      "serverID": 17662304,
      "targetIndex": 352,
      "zoneID": 216
    },
    {
      "name": "Observer",
      "serverID": 17662305,
      "targetIndex": 353,
      "zoneID": 216
    },
    {
      "name": "Observer",
      "serverID": 17662306,
      "targetIndex": 354,
      "zoneID": 216
    },
    {
      "name": "Observer",
      "serverID": 17662307,
      "targetIndex": 355,
      "zoneID": 216
    },
    {
      "name": "Observer",
      "serverID": 17662308,
      "targetIndex": 356,
      "zoneID": 216
    },
    {
      "name": "Observer",
      "serverID": 17662309,
      "targetIndex": 357,
      "zoneID": 216
    },
    {
      "name": "Ephemeral Amoeban",
      "serverID": 17662310,
      "targetIndex": 358,
      "zoneID": 216
    },
    {
      "name": "Dynamo Cluster",
      "serverID": 17662311,
      "targetIndex": 359,
      "zoneID": 216
    },
    {
      "name": "Dynamo Cluster",
      "serverID": 17662312,
      "targetIndex": 360,
      "zoneID": 216
    },
    {
      "name": "Dynamo Cluster",
      "serverID": 17662313,
      "targetIndex": 361,
      "zoneID": 216
    },
    {
      "name": "Dynamo Cluster",
      "serverID": 17662314,
      "targetIndex": 362,
      "zoneID": 216
    },
    {
      "name": "Dynamo Cluster",
      "serverID": 17662315,
      "targetIndex": 363,
      "zoneID": 216
    },
    {
      "name": "Dynamo Cluster",
      "serverID": 17662316,
      "targetIndex": 364,
      "zoneID": 216
    },
    {
      "name": "Dynamo Cluster",
      "serverID": 17662317,
      "targetIndex": 365,
      "zoneID": 216
    },
    {
      "name": "Dynamo Cluster",
      "serverID": 17662318,
      "targetIndex": 366,
      "zoneID": 216
    },
    {
      "name": "Dynamo Cluster",
      "serverID": 17662319,
      "targetIndex": 367,
      "zoneID": 216
    },
    {
      "name": "Dynamo Cluster",
      "serverID": 17662320,
      "targetIndex": 368,
      "zoneID": 216
    },
    {
      "name": "Dynamo Cluster",
      "serverID": 17662321,
      "targetIndex": 369,
      "zoneID": 216
    },
    {
      "name": "Dynamo Cluster",
      "serverID": 17662322,
      "targetIndex": 370,
      "zoneID": 216
    },
    {
      "name": "Dynamo Cluster",
      "serverID": 17662323,
      "targetIndex": 371,
      "zoneID": 216
    },
    {
      "name": "Dynamo Cluster",
      "serverID": 17662324,
      "targetIndex": 372,
      "zoneID": 216
    },
    {
      "name": "Dynamo Cluster",
      "serverID": 17662325,
      "targetIndex": 373,
      "zoneID": 216
    },
    {
      "name": "Dynamo Cluster",
      "serverID": 17662326,
      "targetIndex": 374,
      "zoneID": 216
    },
    {
      "name": "Dynamo Cluster",
      "serverID": 17662327,
      "targetIndex": 375,
      "zoneID": 216
    },
    {
      "name": "Dynamo Cluster",
      "serverID": 17662328,
      "targetIndex": 376,
      "zoneID": 216
    },
    {
      "name": "Dynamo Cluster",
      "serverID": 17662329,
      "targetIndex": 377,
      "zoneID": 216
    },
    {
      "name": "Ephemeral Murex",
      "serverID": 17662330,
      "targetIndex": 378,
      "zoneID": 216
    },
    {
      "name": "Atrociraptor",
      "serverID": 17662331,
      "targetIndex": 379,
      "zoneID": 216
    },
    {
      "name": "Atrociraptor",
      "serverID": 17662332,
      "targetIndex": 380,
      "zoneID": 216
    },
    {
      "name": "Atrociraptor",
      "serverID": 17662333,
      "targetIndex": 381,
      "zoneID": 216
    },
    {
      "name": "Atrociraptor",
      "serverID": 17662334,
      "targetIndex": 382,
      "zoneID": 216
    },
    {
      "name": "Atrociraptor",
      "serverID": 17662335,
      "targetIndex": 383,
      "zoneID": 216
    },
    {
      "name": "Atrociraptor",
      "serverID": 17662336,
      "targetIndex": 384,
      "zoneID": 216
    },
    {
      "name": "Atrociraptor",
      "serverID": 17662337,
      "targetIndex": 385,
      "zoneID": 216
    },
    {
      "name": "Atrociraptor",
      "serverID": 17662338,
      "targetIndex": 386,
      "zoneID": 216
    },
    {
      "name": "Atrociraptor",
      "serverID": 17662339,
      "targetIndex": 387,
      "zoneID": 216
    },
    {
      "name": "Atrociraptor",
      "serverID": 17662340,
      "targetIndex": 388,
      "zoneID": 216
    },
    {
      "name": "Atrociraptor",
      "serverID": 17662341,
      "targetIndex": 389,
      "zoneID": 216
    },
    {
      "name": "Atrociraptor",
      "serverID": 17662342,
      "targetIndex": 390,
      "zoneID": 216
    },
    {
      "name": "Atrociraptor",
      "serverID": 17662343,
      "targetIndex": 391,
      "zoneID": 216
    },
    {
      "name": "Atrociraptor",
      "serverID": 17662344,
      "targetIndex": 392,
      "zoneID": 216
    },
    {
      "name": "Atrociraptor",
      "serverID": 17662345,
      "targetIndex": 393,
      "zoneID": 216
    },
    {
      "name": "Atrociraptor",
      "serverID": 17662346,
      "targetIndex": 394,
      "zoneID": 216
    },
    {
      "name": "Atrociraptor",
      "serverID": 17662347,
      "targetIndex": 395,
      "zoneID": 216
    },
    {
      "name": "Atrociraptor",
      "serverID": 17662348,
      "targetIndex": 396,
      "zoneID": 216
    },
    {
      "name": "Atrociraptor",
      "serverID": 17662349,
      "targetIndex": 397,
      "zoneID": 216
    },
    {
      "name": "Atrociraptor",
      "serverID": 17662350,
      "targetIndex": 398,
      "zoneID": 216
    },
    {
      "name": "Atrociraptor",
      "serverID": 17662351,
      "targetIndex": 399,
      "zoneID": 216
    },
    {
      "name": "Atrociraptor",
      "serverID": 17662352,
      "targetIndex": 400,
      "zoneID": 216
    },
    {
      "name": "Atrociraptor",
      "serverID": 17662353,
      "targetIndex": 401,
      "zoneID": 216
    },
    {
      "name": "Atrociraptor",
      "serverID": 17662354,
      "targetIndex": 402,
      "zoneID": 216
    },
    {
      "name": "Atrociraptor",
      "serverID": 17662355,
      "targetIndex": 403,
      "zoneID": 216
    },
    {
      "name": "Atrociraptor",
      "serverID": 17662356,
      "targetIndex": 404,
      "zoneID": 216
    },
    {
      "name": "Atrociraptor",
      "serverID": 17662357,
      "targetIndex": 405,
      "zoneID": 216
    },
    {
      "name": "Ephemeral Amoeban",
      "serverID": 17662358,
      "targetIndex": 406,
      "zoneID": 216
    },
    {
      "name": "Dusk Lizard",
      "serverID": 17662359,
      "targetIndex": 407,
      "zoneID": 216
    },
    {
      "name": "Dusk Lizard",
      "serverID": 17662360,
      "targetIndex": 408,
      "zoneID": 216
    },
    {
      "name": "Dusk Lizard",
      "serverID": 17662361,
      "targetIndex": 409,
      "zoneID": 216
    },
    {
      "name": "Dusk Lizard",
      "serverID": 17662362,
      "targetIndex": 410,
      "zoneID": 216
    },
    {
      "name": "Dusk Lizard",
      "serverID": 17662363,
      "targetIndex": 411,
      "zoneID": 216
    },
    {
      "name": "Dusk Lizard",
      "serverID": 17662364,
      "targetIndex": 412,
      "zoneID": 216
    },
    {
      "name": "Dusk Lizard",
      "serverID": 17662365,
      "targetIndex": 413,
      "zoneID": 216
    },
    {
      "name": "Dusk Lizard",
      "serverID": 17662366,
      "targetIndex": 414,
      "zoneID": 216
    },
    {
      "name": "Dusk Lizard",
      "serverID": 17662367,
      "targetIndex": 415,
      "zoneID": 216
    },
    {
      "name": "Dusk Lizard",
      "serverID": 17662368,
      "targetIndex": 416,
      "zoneID": 216
    },
    {
      "name": "Dusk Lizard",
      "serverID": 17662369,
      "targetIndex": 417,
      "zoneID": 216
    },
    {
      "name": "Dusk Lizard",
      "serverID": 17662370,
      "targetIndex": 418,
      "zoneID": 216
    },
    {
      "name": "Dusk Lizard",
      "serverID": 17662371,
      "targetIndex": 419,
      "zoneID": 216
    },
    {
      "name": "Dusk Lizard",
      "serverID": 17662372,
      "targetIndex": 420,
      "zoneID": 216
    },
    {
      "name": "Dusk Lizard",
      "serverID": 17662373,
      "targetIndex": 421,
      "zoneID": 216
    },
    {
      "name": "Dusk Lizard",
      "serverID": 17662374,
      "targetIndex": 422,
      "zoneID": 216
    },
    {
      "name": "Dusk Lizard",
      "serverID": 17662375,
      "targetIndex": 423,
      "zoneID": 216
    },
    {
      "name": "Dusk Lizard",
      "serverID": 17662376,
      "targetIndex": 424,
      "zoneID": 216
    },
    {
      "name": "Dusk Lizard",
      "serverID": 17662377,
      "targetIndex": 425,
      "zoneID": 216
    },
    {
      "name": "Dusk Lizard",
      "serverID": 17662378,
      "targetIndex": 426,
      "zoneID": 216
    },
    {
      "name": "Dusk Lizard",
      "serverID": 17662379,
      "targetIndex": 427,
      "zoneID": 216
    },
    {
      "name": "Ephemeral Murex",
      "serverID": 17662380,
      "targetIndex": 428,
      "zoneID": 216
    },
    {
      "name": "Maritime Peiste",
      "serverID": 17662381,
      "targetIndex": 429,
      "zoneID": 216
    },
    {
      "name": "Maritime Peiste",
      "serverID": 17662382,
      "targetIndex": 430,
      "zoneID": 216
    },
    {
      "name": "Maritime Peiste",
      "serverID": 17662383,
      "targetIndex": 431,
      "zoneID": 216
    },
    {
      "name": "Maritime Peiste",
      "serverID": 17662384,
      "targetIndex": 432,
      "zoneID": 216
    },
    {
      "name": "Maritime Peiste",
      "serverID": 17662385,
      "targetIndex": 433,
      "zoneID": 216
    },
    {
      "name": "Maritime Peiste",
      "serverID": 17662386,
      "targetIndex": 434,
      "zoneID": 216
    },
    {
      "name": "Maritime Peiste",
      "serverID": 17662387,
      "targetIndex": 435,
      "zoneID": 216
    },
    {
      "name": "Maritime Peiste",
      "serverID": 17662388,
      "targetIndex": 436,
      "zoneID": 216
    },
    {
      "name": "Maritime Peiste",
      "serverID": 17662389,
      "targetIndex": 437,
      "zoneID": 216
    },
    {
      "name": "Maritime Peiste",
      "serverID": 17662390,
      "targetIndex": 438,
      "zoneID": 216
    },
    {
      "name": "Maritime Peiste",
      "serverID": 17662391,
      "targetIndex": 439,
      "zoneID": 216
    },
    {
      "name": "Maritime Peiste",
      "serverID": 17662392,
      "targetIndex": 440,
      "zoneID": 216
    },
    {
      "name": "Maritime Peiste",
      "serverID": 17662393,
      "targetIndex": 441,
      "zoneID": 216
    },
    {
      "name": "Maritime Peiste",
      "serverID": 17662394,
      "targetIndex": 442,
      "zoneID": 216
    },
    {
      "name": "Maritime Peiste",
      "serverID": 17662395,
      "targetIndex": 443,
      "zoneID": 216
    },
    {
      "name": "Maritime Peiste",
      "serverID": 17662396,
      "targetIndex": 444,
      "zoneID": 216
    },
    {
      "name": "Maritime Peiste",
      "serverID": 17662397,
      "targetIndex": 445,
      "zoneID": 216
    },
    {
      "name": "Maritime Peiste",
      "serverID": 17662398,
      "targetIndex": 446,
      "zoneID": 216
    },
    {
      "name": "Maritime Peiste",
      "serverID": 17662399,
      "targetIndex": 447,
      "zoneID": 216
    },
    {
      "name": "Maritime Peiste",
      "serverID": 17662400,
      "targetIndex": 448,
      "zoneID": 216
    },
    {
      "name": "Maritime Peiste",
      "serverID": 17662401,
      "targetIndex": 449,
      "zoneID": 216
    },
    {
      "name": "Ephemeral Amoeban",
      "serverID": 17662402,
      "targetIndex": 450,
      "zoneID": 216
    },
    {
      "name": "Abyssobugard",
      "serverID": 17662403,
      "targetIndex": 451,
      "zoneID": 216
    },
    {
      "name": "Abyssobugard",
      "serverID": 17662404,
      "targetIndex": 452,
      "zoneID": 216
    },
    {
      "name": "Abyssobugard",
      "serverID": 17662405,
      "targetIndex": 453,
      "zoneID": 216
    },
    {
      "name": "Abyssobugard",
      "serverID": 17662406,
      "targetIndex": 454,
      "zoneID": 216
    },
    {
      "name": "Abyssobugard",
      "serverID": 17662407,
      "targetIndex": 455,
      "zoneID": 216
    },
    {
      "name": "Abyssobugard",
      "serverID": 17662408,
      "targetIndex": 456,
      "zoneID": 216
    },
    {
      "name": "Abyssobugard",
      "serverID": 17662409,
      "targetIndex": 457,
      "zoneID": 216
    },
    {
      "name": "Abyssobugard",
      "serverID": 17662410,
      "targetIndex": 458,
      "zoneID": 216
    },
    {
      "name": "Abyssobugard",
      "serverID": 17662411,
      "targetIndex": 459,
      "zoneID": 216
    },
    {
      "name": "Abyssobugard",
      "serverID": 17662412,
      "targetIndex": 460,
      "zoneID": 216
    },
    {
      "name": "Abyssobugard",
      "serverID": 17662413,
      "targetIndex": 461,
      "zoneID": 216
    },
    {
      "name": "Abyssobugard",
      "serverID": 17662414,
      "targetIndex": 462,
      "zoneID": 216
    },
    {
      "name": "Abyssobugard",
      "serverID": 17662415,
      "targetIndex": 463,
      "zoneID": 216
    },
    {
      "name": "Abyssobugard",
      "serverID": 17662416,
      "targetIndex": 464,
      "zoneID": 216
    },
    {
      "name": "Abyssobugard",
      "serverID": 17662417,
      "targetIndex": 465,
      "zoneID": 216
    },
    {
      "name": "Abyssobugard",
      "serverID": 17662418,
      "targetIndex": 466,
      "zoneID": 216
    },
    {
      "name": "Abyssobugard",
      "serverID": 17662419,
      "targetIndex": 467,
      "zoneID": 216
    },
    {
      "name": "Abyssobugard",
      "serverID": 17662420,
      "targetIndex": 468,
      "zoneID": 216
    },
    {
      "name": "Abyssobugard",
      "serverID": 17662421,
      "targetIndex": 469,
      "zoneID": 216
    },
    {
      "name": "Abyssobugard",
      "serverID": 17662422,
      "targetIndex": 470,
      "zoneID": 216
    },
    {
      "name": "Abyssobugard",
      "serverID": 17662423,
      "targetIndex": 471,
      "zoneID": 216
    },
    {
      "name": "Ephemeral Murex",
      "serverID": 17662424,
      "targetIndex": 472,
      "zoneID": 216
    },
    {
      "name": "Orapodium",
      "serverID": 17662425,
      "targetIndex": 473,
      "zoneID": 216
    },
    {
      "name": "Orapodium",
      "serverID": 17662426,
      "targetIndex": 474,
      "zoneID": 216
    },
    {
      "name": "Orapodium",
      "serverID": 17662427,
      "targetIndex": 475,
      "zoneID": 216
    },
    {
      "name": "Orapodium",
      "serverID": 17662428,
      "targetIndex": 476,
      "zoneID": 216
    },
    {
      "name": "Orapodium",
      "serverID": 17662429,
      "targetIndex": 477,
      "zoneID": 216
    },
    {
      "name": "Orapodium",
      "serverID": 17662430,
      "targetIndex": 478,
      "zoneID": 216
    },
    {
      "name": "Orapodium",
      "serverID": 17662431,
      "targetIndex": 479,
      "zoneID": 216
    },
    {
      "name": "Orapodium",
      "serverID": 17662432,
      "targetIndex": 480,
      "zoneID": 216
    },
    {
      "name": "Orapodium",
      "serverID": 17662433,
      "targetIndex": 481,
      "zoneID": 216
    },
    {
      "name": "Orapodium",
      "serverID": 17662434,
      "targetIndex": 482,
      "zoneID": 216
    },
    {
      "name": "Orapodium",
      "serverID": 17662435,
      "targetIndex": 483,
      "zoneID": 216
    },
    {
      "name": "Orapodium",
      "serverID": 17662436,
      "targetIndex": 484,
      "zoneID": 216
    },
    {
      "name": "Orapodium",
      "serverID": 17662437,
      "targetIndex": 485,
      "zoneID": 216
    },
    {
      "name": "Orapodium",
      "serverID": 17662438,
      "targetIndex": 486,
      "zoneID": 216
    },
    {
      "name": "Orapodium",
      "serverID": 17662439,
      "targetIndex": 487,
      "zoneID": 216
    },
    {
      "name": "Orapodium",
      "serverID": 17662440,
      "targetIndex": 488,
      "zoneID": 216
    },
    {
      "name": "Orapodium",
      "serverID": 17662441,
      "targetIndex": 489,
      "zoneID": 216
    },
    {
      "name": "Orapodium",
      "serverID": 17662442,
      "targetIndex": 490,
      "zoneID": 216
    },
    {
      "name": "Orapodium",
      "serverID": 17662443,
      "targetIndex": 491,
      "zoneID": 216
    },
    {
      "name": "Orapodium",
      "serverID": 17662444,
      "targetIndex": 492,
      "zoneID": 216
    },
    {
      "name": "Orapodium",
      "serverID": 17662445,
      "targetIndex": 493,
      "zoneID": 216
    },
    {
      "name": "Orapodium",
      "serverID": 17662446,
      "targetIndex": 494,
      "zoneID": 216
    },
    {
      "name": "Orapodium",
      "serverID": 17662447,
      "targetIndex": 495,
      "zoneID": 216
    },
    {
      "name": "Orapodium",
      "serverID": 17662448,
      "targetIndex": 496,
      "zoneID": 216
    },
    {
      "name": "Orapodium",
      "serverID": 17662449,
      "targetIndex": 497,
      "zoneID": 216
    },
    {
      "name": "Ephemeral Amoeban",
      "serverID": 17662450,
      "targetIndex": 498,
      "zoneID": 216
    },
    {
      "name": "Jala",
      "serverID": 17662451,
      "targetIndex": 499,
      "zoneID": 216
    },
    {
      "name": "Jala",
      "serverID": 17662452,
      "targetIndex": 500,
      "zoneID": 216
    },
    {
      "name": "Jala",
      "serverID": 17662453,
      "targetIndex": 501,
      "zoneID": 216
    },
    {
      "name": "Jala",
      "serverID": 17662454,
      "targetIndex": 502,
      "zoneID": 216
    },
    {
      "name": "Jala",
      "serverID": 17662455,
      "targetIndex": 503,
      "zoneID": 216
    },
    {
      "name": "Tristitia",
      "serverID": 17662456,
      "targetIndex": 504,
      "zoneID": 216
    },
    {
      "name": "Mx'ghrah",
      "serverID": 17662457,
      "targetIndex": 505,
      "zoneID": 216
    },
    {
      "name": "Mi'ghrah",
      "serverID": 17662458,
      "targetIndex": 506,
      "zoneID": 216
    },
    {
      "name": "Mi'ghrah",
      "serverID": 17662459,
      "targetIndex": 507,
      "zoneID": 216
    },
    {
      "name": "Mi'ghrah",
      "serverID": 17662460,
      "targetIndex": 508,
      "zoneID": 216
    },
    {
      "name": "Mi'ghrah",
      "serverID": 17662461,
      "targetIndex": 509,
      "zoneID": 216
    },
    {
      "name": "Mi'ghrah",
      "serverID": 17662462,
      "targetIndex": 510,
      "zoneID": 216
    },
    {
      "name": "Mi'ghrah",
      "serverID": 17662463,
      "targetIndex": 511,
      "zoneID": 216
    },
    {
      "name": "Minax Bugard",
      "serverID": 17662464,
      "targetIndex": 512,
      "zoneID": 216
    },
    {
      "name": "Sirrush",
      "serverID": 17662465,
      "targetIndex": 513,
      "zoneID": 216
    },
    {
      "name": "Funereal Apkallu",
      "serverID": 17662466,
      "targetIndex": 514,
      "zoneID": 216
    },
    {
      "name": "Manohra",
      "serverID": 17662467,
      "targetIndex": 515,
      "zoneID": 216
    },
    {
      "name": "Cep-Kamuy",
      "serverID": 17662468,
      "targetIndex": 516,
      "zoneID": 216
    },
    {
      "name": "Ironclad Observer",
      "serverID": 17662469,
      "targetIndex": 517,
      "zoneID": 216
    },
    {
      "name": "Nehebkau",
      "serverID": 17662470,
      "targetIndex": 518,
      "zoneID": 216
    },
    {
      "name": "Avalerion",
      "serverID": 17662471,
      "targetIndex": 519,
      "zoneID": 216
    },
    {
      "name": "Karkatakam",
      "serverID": 17662472,
      "targetIndex": 520,
      "zoneID": 216
    },
    {
      "name": "Nonno",
      "serverID": 17662473,
      "targetIndex": 521,
      "zoneID": 216
    },
    {
      "name": "Tuskertrap",
      "serverID": 17662474,
      "targetIndex": 522,
      "zoneID": 216
    },
    {
      "name": "Npfundlwa",
      "serverID": 17662475,
      "targetIndex": 523,
      "zoneID": 216
    },
    {
      "name": "Cirein-croin",
      "serverID": 17662476,
      "targetIndex": 524,
      "zoneID": 216
    },
    {
      "name": "Amhuluk",
      "serverID": 17662477,
      "targetIndex": 525,
      "zoneID": 216
    },
    {
      "name": "Sobek",
      "serverID": 17662478,
      "targetIndex": 526,
      "zoneID": 216
    },
    {
      "name": "Ironclad Pulverizer",
      "serverID": 17662479,
      "targetIndex": 527,
      "zoneID": 216
    },
    {
      "name": "Ironclad Pulverizer",
      "serverID": 17662480,
      "targetIndex": 528,
      "zoneID": 216
    },
    {
      "name": "Cirein-croin",
      "serverID": 17662481,
      "targetIndex": 529,
      "zoneID": 216
    },
    {
      "name": "Amhuluk",
      "serverID": 17662482,
      "targetIndex": 530,
      "zoneID": 216
    },
    {
      "name": "Sobek",
      "serverID": 17662483,
      "targetIndex": 531,
      "zoneID": 216
    },
    {
      "name": "Ironclad Pulverizer",
      "serverID": 17662484,
      "targetIndex": 532,
      "zoneID": 216
    },
    {
      "name": "Ironclad Pulverizer",
      "serverID": 17662485,
      "targetIndex": 533,
      "zoneID": 216
    },
    {
      "name": "Cirein-croin",
      "serverID": 17662486,
      "targetIndex": 534,
      "zoneID": 216
    },
    {
      "name": "Amhuluk",
      "serverID": 17662487,
      "targetIndex": 535,
      "zoneID": 216
    },
    {
      "name": "Sobek",
      "serverID": 17662488,
      "targetIndex": 536,
      "zoneID": 216
    },
    {
      "name": "Ironclad Pulverizer",
      "serverID": 17662489,
      "targetIndex": 537,
      "zoneID": 216
    },
    {
      "name": "Ironclad Pulverizer",
      "serverID": 17662490,
      "targetIndex": 538,
      "zoneID": 216
    },
    {
      "name": "Gukumatz",
      "serverID": 17662491,
      "targetIndex": 539,
      "zoneID": 216
    },
    {
      "name": "Asanbosam",
      "serverID": 17662492,
      "targetIndex": 540,
      "zoneID": 216
    },
    {
      "name": "Heqet",
      "serverID": 17662493,
      "targetIndex": 541,
      "zoneID": 216
    },
    {
      "name": "Abyssic Cluster",
      "serverID": 17662494,
      "targetIndex": 542,
      "zoneID": 216
    },
    {
      "name": "Flame Skimmer",
      "serverID": 17662495,
      "targetIndex": 543,
      "zoneID": 216
    },
    {
      "name": "Athamas",
      "serverID": 17662496,
      "targetIndex": 544,
      "zoneID": 216
    },
    {
      "name": "Kutharei",
      "serverID": 17662497,
      "targetIndex": 545,
      "zoneID": 216
    },
    {
      "name": "Ironclad Severer",
      "serverID": 17662498,
      "targetIndex": 546,
      "zoneID": 216
    },
    {
      "name": "Sturdy Pyxis",
      "serverID": 17662499,
      "targetIndex": 547,
      "zoneID": 216
    },
    {
      "name": "Sturdy Pyxis",
      "serverID": 17662500,
      "targetIndex": 548,
      "zoneID": 216
    },
    {
      "name": "Sturdy Pyxis",
      "serverID": 17662501,
      "targetIndex": 549,
      "zoneID": 216
    },
    {
      "name": "Sturdy Pyxis",
      "serverID": 17662502,
      "targetIndex": 550,
      "zoneID": 216
    },
    {
      "name": "Surveyor",
      "serverID": 17662503,
      "targetIndex": 551,
      "zoneID": 216
    },
    {
      "name": "Surveyor",
      "serverID": 17662504,
      "targetIndex": 552,
      "zoneID": 216
    },
    {
      "name": "Scrutinizer",
      "serverID": 17662505,
      "targetIndex": 553,
      "zoneID": 216
    },
    {
      "name": "Scrutinizer",
      "serverID": 17662506,
      "targetIndex": 554,
      "zoneID": 216
    },
    {
      "name": "Decontaminator",
      "serverID": 17662507,
      "targetIndex": 555,
      "zoneID": 216
    },
    {
      "name": "Decontaminator",
      "serverID": 17662508,
      "targetIndex": 556,
      "zoneID": 216
    },
    {
      "name": "Vigilant Gears",
      "serverID": 17662509,
      "targetIndex": 557,
      "zoneID": 216
    },
    {
      "name": "Vigilant Gears",
      "serverID": 17662510,
      "targetIndex": 558,
      "zoneID": 216
    },
    {
      "name": "Immobilizer",
      "serverID": 17662511,
      "targetIndex": 559,
      "zoneID": 216
    },
    {
      "name": "Disassembler",
      "serverID": 17662512,
      "targetIndex": 560,
      "zoneID": 216
    },
    {
      "name": "Oppressor",
      "serverID": 17662513,
      "targetIndex": 561,
      "zoneID": 216
    },
    {
      "name": "Edifier",
      "serverID": 17662514,
      "targetIndex": 562,
      "zoneID": 216
    },
    {
      "name": "Overseer",
      "serverID": 17662515,
      "targetIndex": 563,
      "zoneID": 216
    },
    {
      "name": "Surveyor",
      "serverID": 17662516,
      "targetIndex": 564,
      "zoneID": 216
    },
    {
      "name": "Surveyor",
      "serverID": 17662517,
      "targetIndex": 565,
      "zoneID": 216
    },
    {
      "name": "Scrutinizer",
      "serverID": 17662518,
      "targetIndex": 566,
      "zoneID": 216
    },
    {
      "name": "Scrutinizer",
      "serverID": 17662519,
      "targetIndex": 567,
      "zoneID": 216
    },
    {
      "name": "Vigilant Gear",
      "serverID": 17662520,
      "targetIndex": 568,
      "zoneID": 216
    },
    {
      "name": "Vigilant Gear",
      "serverID": 17662521,
      "targetIndex": 569,
      "zoneID": 216
    },
    {
      "name": "Earth Mover",
      "serverID": 17662522,
      "targetIndex": 570,
      "zoneID": 216
    },
    {
      "name": "Earth Mover",
      "serverID": 17662523,
      "targetIndex": 571,
      "zoneID": 216
    },
    {
      "name": "Immobilizer",
      "serverID": 17662524,
      "targetIndex": 572,
      "zoneID": 216
    },
    {
      "name": "Disassembler",
      "serverID": 17662525,
      "targetIndex": 573,
      "zoneID": 216
    },
    {
      "name": "Oppressor",
      "serverID": 17662526,
      "targetIndex": 574,
      "zoneID": 216
    },
    {
      "name": "Edifier",
      "serverID": 17662527,
      "targetIndex": 575,
      "zoneID": 216
    },
    {
      "name": "Overseer",
      "serverID": 17662528,
      "targetIndex": 576,
      "zoneID": 216
    },
    {
      "name": "Surveyor",
      "serverID": 17662529,
      "targetIndex": 577,
      "zoneID": 216
    },
    {
      "name": "Surveyor",
      "serverID": 17662530,
      "targetIndex": 578,
      "zoneID": 216
    },
    {
      "name": "Scrutinizer",
      "serverID": 17662531,
      "targetIndex": 579,
      "zoneID": 216
    },
    {
      "name": "Scrutinizer",
      "serverID": 17662532,
      "targetIndex": 580,
      "zoneID": 216
    },
    {
      "name": "Custodian",
      "serverID": 17662533,
      "targetIndex": 581,
      "zoneID": 216
    },
    {
      "name": "Custodian",
      "serverID": 17662534,
      "targetIndex": 582,
      "zoneID": 216
    },
    {
      "name": "Ravager Chariot",
      "serverID": 17662535,
      "targetIndex": 583,
      "zoneID": 216
    },
    {
      "name": "Ravager Chariot",
      "serverID": 17662536,
      "targetIndex": 584,
      "zoneID": 216
    },
    {
      "name": "Immobilizer",
      "serverID": 17662537,
      "targetIndex": 585,
      "zoneID": 216
    },
    {
      "name": "Disassembler",
      "serverID": 17662538,
      "targetIndex": 586,
      "zoneID": 216
    },
    {
      "name": "Oppressor",
      "serverID": 17662539,
      "targetIndex": 587,
      "zoneID": 216
    },
    {
      "name": "Edifier",
      "serverID": 17662540,
      "targetIndex": 588,
      "zoneID": 216
    },
    {
      "name": "Overseer",
      "serverID": 17662541,
      "targetIndex": 589,
      "zoneID": 216
    },
    {
      "name": "Bastion Fighter",
      "serverID": 17662542,
      "targetIndex": 590,
      "zoneID": 216
    },
    {
      "name": "Bastion Fighter",
      "serverID": 17662543,
      "targetIndex": 591,
      "zoneID": 216
    },
    {
      "name": "Bastion Fighter",
      "serverID": 17662544,
      "targetIndex": 592,
      "zoneID": 216
    },
    {
      "name": "Bastion Fighter",
      "serverID": 17662545,
      "targetIndex": 593,
      "zoneID": 216
    },
    {
      "name": "Bastion Fighter",
      "serverID": 17662546,
      "targetIndex": 594,
      "zoneID": 216
    },
    {
      "name": "Bastion Mage",
      "serverID": 17662547,
      "targetIndex": 595,
      "zoneID": 216
    },
    {
      "name": "Bastion Mage",
      "serverID": 17662548,
      "targetIndex": 596,
      "zoneID": 216
    },
    {
      "name": "Bastion Mage",
      "serverID": 17662549,
      "targetIndex": 597,
      "zoneID": 216
    },
    {
      "name": "Qiqirn Trapper",
      "serverID": 17662550,
      "targetIndex": 598,
      "zoneID": 216
    },
    {
      "name": "Qiqirn Trapper",
      "serverID": 17662551,
      "targetIndex": 599,
      "zoneID": 216
    },
    {
      "name": "Qiqirn Bewitcher",
      "serverID": 17662552,
      "targetIndex": 600,
      "zoneID": 216
    },
    {
      "name": "Qiqirn Bewitcher",
      "serverID": 17662553,
      "targetIndex": 601,
      "zoneID": 216
    },
    {
      "name": "???",
      "serverID": 17662556,
      "targetIndex": 604,
      "zoneID": 216
    },
    {
      "name": "???",
      "serverID": 17662557,
      "targetIndex": 605,
      "zoneID": 216
    },
    {
      "name": "???",
      "serverID": 17662558,
      "targetIndex": 606,
      "zoneID": 216
    },
    {
      "name": "???",
      "serverID": 17662559,
      "targetIndex": 607,
      "zoneID": 216
    },
    {
      "name": "???",
      "serverID": 17662560,
      "targetIndex": 608,
      "zoneID": 216
    },
    {
      "name": "???",
      "serverID": 17662561,
      "targetIndex": 609,
      "zoneID": 216
    },
    {
      "name": "???",
      "serverID": 17662562,
      "targetIndex": 610,
      "zoneID": 216
    },
    {
      "name": "???",
      "serverID": 17662563,
      "targetIndex": 611,
      "zoneID": 216
    },
    {
      "name": "???",
      "serverID": 17662564,
      "targetIndex": 612,
      "zoneID": 216
    },
    {
      "name": "???",
      "serverID": 17662565,
      "targetIndex": 613,
      "zoneID": 216
    },
    {
      "name": "???",
      "serverID": 17662566,
      "targetIndex": 614,
      "zoneID": 216
    },
    {
      "name": "???",
      "serverID": 17662567,
      "targetIndex": 615,
      "zoneID": 216
    },
    {
      "name": "???",
      "serverID": 17662568,
      "targetIndex": 616,
      "zoneID": 216
    },
    {
      "name": "???",
      "serverID": 17662569,
      "targetIndex": 617,
      "zoneID": 216
    },
    {
      "name": "???",
      "serverID": 17662570,
      "targetIndex": 618,
      "zoneID": 216
    },
    {
      "name": "???",
      "serverID": 17662571,
      "targetIndex": 619,
      "zoneID": 216
    },
    {
      "name": "???",
      "serverID": 17662572,
      "targetIndex": 620,
      "zoneID": 216
    },
    {
      "name": "???",
      "serverID": 17662573,
      "targetIndex": 621,
      "zoneID": 216
    },
    {
      "name": "???",
      "serverID": 17662574,
      "targetIndex": 622,
      "zoneID": 216
    },
    {
      "name": "???",
      "serverID": 17662575,
      "targetIndex": 623,
      "zoneID": 216
    },
    {
      "name": "???",
      "serverID": 17662576,
      "targetIndex": 624,
      "zoneID": 216
    },
    {
      "name": "???",
      "serverID": 17662577,
      "targetIndex": 625,
      "zoneID": 216
    },
    {
      "name": "???",
      "serverID": 17662578,
      "targetIndex": 626,
      "zoneID": 216
    },
    {
      "name": "???",
      "serverID": 17662579,
      "targetIndex": 627,
      "zoneID": 216
    },
    {
      "name": "Achieve Master",
      "serverID": 17662581,
      "targetIndex": 629,
      "zoneID": 216
    },
    {
      "name": "Unity Master",
      "serverID": 17662582,
      "targetIndex": 630,
      "zoneID": 216
    },
    {
      "name": "Conflux Surveyor",
      "serverID": 17662587,
      "targetIndex": 635,
      "zoneID": 216
    },
    {
      "name": "Cruor Prospector",
      "serverID": 17662588,
      "targetIndex": 636,
      "zoneID": 216
    },
    {
      "name": "Atma Infusionist",
      "serverID": 17662589,
      "targetIndex": 637,
      "zoneID": 216
    },
    {
      "name": "Atma Fabricant",
      "serverID": 17662590,
      "targetIndex": 638,
      "zoneID": 216
    },
    {
      "name": "Time Master Debug",
      "serverID": 17662591,
      "targetIndex": 639,
      "zoneID": 216
    },
    {
      "name": "AP Master Debug",
      "serverID": 17662592,
      "targetIndex": 640,
      "zoneID": 216
    },
    {
      "name": "Sturdy Pyxis",
      "serverID": 17662595,
      "targetIndex": 643,
      "zoneID": 216
    },
    {
      "name": "Sturdy Pyxis",
      "serverID": 17662596,
      "targetIndex": 644,
      "zoneID": 216
    },
    {
      "name": "Sturdy Pyxis",
      "serverID": 17662597,
      "targetIndex": 645,
      "zoneID": 216
    },
    {
      "name": "Sturdy Pyxis",
      "serverID": 17662598,
      "targetIndex": 646,
      "zoneID": 216
    },
    {
      "name": "Sturdy Pyxis",
      "serverID": 17662599,
      "targetIndex": 647,
      "zoneID": 216
    },
    {
      "name": "Sturdy Pyxis",
      "serverID": 17662600,
      "targetIndex": 648,
      "zoneID": 216
    },
    {
      "name": "Sturdy Pyxis",
      "serverID": 17662601,
      "targetIndex": 649,
      "zoneID": 216
    },
    {
      "name": "Sturdy Pyxis",
      "serverID": 17662602,
      "targetIndex": 650,
      "zoneID": 216
    },
    {
      "name": "Sturdy Pyxis",
      "serverID": 17662603,
      "targetIndex": 651,
      "zoneID": 216
    },
    {
      "name": "Sturdy Pyxis",
      "serverID": 17662604,
      "targetIndex": 652,
      "zoneID": 216
    },
    {
      "name": "Sturdy Pyxis",
      "serverID": 17662605,
      "targetIndex": 653,
      "zoneID": 216
    },
    {
      "name": "Sturdy Pyxis",
      "serverID": 17662606,
      "targetIndex": 654,
      "zoneID": 216
    },
    {
      "name": "Sturdy Pyxis",
      "serverID": 17662607,
      "targetIndex": 655,
      "zoneID": 216
    },
    {
      "name": "Sturdy Pyxis",
      "serverID": 17662608,
      "targetIndex": 656,
      "zoneID": 216
    },
    {
      "name": "Sturdy Pyxis",
      "serverID": 17662609,
      "targetIndex": 657,
      "zoneID": 216
    },
    {
      "name": "Sturdy Pyxis",
      "serverID": 17662610,
      "targetIndex": 658,
      "zoneID": 216
    },
    {
      "name": "Sturdy Pyxis",
      "serverID": 17662611,
      "targetIndex": 659,
      "zoneID": 216
    },
    {
      "name": "Sturdy Pyxis",
      "serverID": 17662612,
      "targetIndex": 660,
      "zoneID": 216
    },
    {
      "name": "Sturdy Pyxis",
      "serverID": 17662613,
      "targetIndex": 661,
      "zoneID": 216
    },
    {
      "name": "Sturdy Pyxis",
      "serverID": 17662614,
      "targetIndex": 662,
      "zoneID": 216
    },
    {
      "name": "Sturdy Pyxis",
      "serverID": 17662615,
      "targetIndex": 663,
      "zoneID": 216
    },
    {
      "name": "Sturdy Pyxis",
      "serverID": 17662616,
      "targetIndex": 664,
      "zoneID": 216
    },
    {
      "name": "Sturdy Pyxis",
      "serverID": 17662617,
      "targetIndex": 665,
      "zoneID": 216
    },
    {
      "name": "Sturdy Pyxis",
      "serverID": 17662618,
      "targetIndex": 666,
      "zoneID": 216
    },
    {
      "name": "Sturdy Pyxis",
      "serverID": 17662619,
      "targetIndex": 667,
      "zoneID": 216
    },
    {
      "name": "Sturdy Pyxis",
      "serverID": 17662620,
      "targetIndex": 668,
      "zoneID": 216
    },
    {
      "name": "Sturdy Pyxis",
      "serverID": 17662621,
      "targetIndex": 669,
      "zoneID": 216
    },
    {
      "name": "Sturdy Pyxis",
      "serverID": 17662622,
      "targetIndex": 670,
      "zoneID": 216
    },
    {
      "name": "Sturdy Pyxis",
      "serverID": 17662623,
      "targetIndex": 671,
      "zoneID": 216
    },
    {
      "name": "Sturdy Pyxis",
      "serverID": 17662624,
      "targetIndex": 672,
      "zoneID": 216
    },
    {
      "name": "Sturdy Pyxis",
      "serverID": 17662625,
      "targetIndex": 673,
      "zoneID": 216
    },
    {
      "name": "Sturdy Pyxis",
      "serverID": 17662626,
      "targetIndex": 674,
      "zoneID": 216
    },
    {
      "name": "Sturdy Pyxis",
      "serverID": 17662627,
      "targetIndex": 675,
      "zoneID": 216
    },
    {
      "name": "Sturdy Pyxis",
      "serverID": 17662628,
      "targetIndex": 676,
      "zoneID": 216
    },
    {
      "name": "Sturdy Pyxis",
      "serverID": 17662629,
      "targetIndex": 677,
      "zoneID": 216
    },
    {
      "name": "Sturdy Pyxis",
      "serverID": 17662630,
      "targetIndex": 678,
      "zoneID": 216
    },
    {
      "name": "Sturdy Pyxis",
      "serverID": 17662631,
      "targetIndex": 679,
      "zoneID": 216
    },
    {
      "name": "Sturdy Pyxis",
      "serverID": 17662632,
      "targetIndex": 680,
      "zoneID": 216
    },
    {
      "name": "Sturdy Pyxis",
      "serverID": 17662633,
      "targetIndex": 681,
      "zoneID": 216
    },
    {
      "name": "Sturdy Pyxis",
      "serverID": 17662634,
      "targetIndex": 682,
      "zoneID": 216
    },
    {
      "name": "Sturdy Pyxis",
      "serverID": 17662635,
      "targetIndex": 683,
      "zoneID": 216
    },
    {
      "name": "Sturdy Pyxis",
      "serverID": 17662636,
      "targetIndex": 684,
      "zoneID": 216
    },
    {
      "name": "Sturdy Pyxis",
      "serverID": 17662637,
      "targetIndex": 685,
      "zoneID": 216
    },
    {
      "name": "Sturdy Pyxis",
      "serverID": 17662638,
      "targetIndex": 686,
      "zoneID": 216
    },
    {
      "name": "Sturdy Pyxis",
      "serverID": 17662639,
      "targetIndex": 687,
      "zoneID": 216
    },
    {
      "name": "Sturdy Pyxis",
      "serverID": 17662640,
      "targetIndex": 688,
      "zoneID": 216
    },
    {
      "name": "Sturdy Pyxis",
      "serverID": 17662641,
      "targetIndex": 689,
      "zoneID": 216
    },
    {
      "name": "Sturdy Pyxis",
      "serverID": 17662642,
      "targetIndex": 690,
      "zoneID": 216
    },
    {
      "name": "Sturdy Pyxis",
      "serverID": 17662643,
      "targetIndex": 691,
      "zoneID": 216
    },
    {
      "name": "Sturdy Pyxis",
      "serverID": 17662644,
      "targetIndex": 692,
      "zoneID": 216
    },
    {
      "name": "Sturdy Pyxis",
      "serverID": 17662645,
      "targetIndex": 693,
      "zoneID": 216
    },
    {
      "name": "Sturdy Pyxis",
      "serverID": 17662646,
      "targetIndex": 694,
      "zoneID": 216
    },
    {
      "name": "Sturdy Pyxis",
      "serverID": 17662647,
      "targetIndex": 695,
      "zoneID": 216
    },
    {
      "name": "Sturdy Pyxis",
      "serverID": 17662648,
      "targetIndex": 696,
      "zoneID": 216
    },
    {
      "name": "Sturdy Pyxis",
      "serverID": 17662649,
      "targetIndex": 697,
      "zoneID": 216
    },
    {
      "name": "Sturdy Pyxis",
      "serverID": 17662650,
      "targetIndex": 698,
      "zoneID": 216
    },
    {
      "name": "Sturdy Pyxis",
      "serverID": 17662651,
      "targetIndex": 699,
      "zoneID": 216
    },
    {
      "name": "Sturdy Pyxis",
      "serverID": 17662652,
      "targetIndex": 700,
      "zoneID": 216
    },
    {
      "name": "Sturdy Pyxis",
      "serverID": 17662653,
      "targetIndex": 701,
      "zoneID": 216
    },
    {
      "name": "Sturdy Pyxis",
      "serverID": 17662654,
      "targetIndex": 702,
      "zoneID": 216
    },
    {
      "name": "Sturdy Pyxis",
      "serverID": 17662655,
      "targetIndex": 703,
      "zoneID": 216
    },
    {
      "name": "Sturdy Pyxis",
      "serverID": 17662656,
      "targetIndex": 704,
      "zoneID": 216
    },
    {
      "name": "Sturdy Pyxis",
      "serverID": 17662657,
      "targetIndex": 705,
      "zoneID": 216
    },
    {
      "name": "Sturdy Pyxis",
      "serverID": 17662658,
      "targetIndex": 706,
      "zoneID": 216
    },
    {
      "name": "Sturdy Pyxis",
      "serverID": 17662659,
      "targetIndex": 707,
      "zoneID": 216
    },
    {
      "name": "Sturdy Pyxis",
      "serverID": 17662660,
      "targetIndex": 708,
      "zoneID": 216
    },
    {
      "name": "Sturdy Pyxis",
      "serverID": 17662661,
      "targetIndex": 709,
      "zoneID": 216
    },
    {
      "name": "Sturdy Pyxis",
      "serverID": 17662662,
      "targetIndex": 710,
      "zoneID": 216
    },
    {
      "name": "Sturdy Pyxis",
      "serverID": 17662663,
      "targetIndex": 711,
      "zoneID": 216
    },
    {
      "name": "Sturdy Pyxis",
      "serverID": 17662664,
      "targetIndex": 712,
      "zoneID": 216
    },
    {
      "name": "Sturdy Pyxis",
      "serverID": 17662665,
      "targetIndex": 713,
      "zoneID": 216
    },
    {
      "name": "Sturdy Pyxis",
      "serverID": 17662666,
      "targetIndex": 714,
      "zoneID": 216
    },
    {
      "name": "Sturdy Pyxis",
      "serverID": 17662667,
      "targetIndex": 715,
      "zoneID": 216
    },
    {
      "name": "Sturdy Pyxis",
      "serverID": 17662668,
      "targetIndex": 716,
      "zoneID": 216
    },
    {
      "name": "Sturdy Pyxis",
      "serverID": 17662669,
      "targetIndex": 717,
      "zoneID": 216
    },
    {
      "name": "Sturdy Pyxis",
      "serverID": 17662670,
      "targetIndex": 718,
      "zoneID": 216
    },
    {
      "name": "Sturdy Pyxis",
      "serverID": 17662671,
      "targetIndex": 719,
      "zoneID": 216
    },
    {
      "name": "Sturdy Pyxis",
      "serverID": 17662672,
      "targetIndex": 720,
      "zoneID": 216
    },
    {
      "name": "Sturdy Pyxis",
      "serverID": 17662673,
      "targetIndex": 721,
      "zoneID": 216
    },
    {
      "name": "Sturdy Pyxis",
      "serverID": 17662674,
      "targetIndex": 722,
      "zoneID": 216
    },
    {
      "name": "Veridical Conflux #01",
      "serverID": 17662675,
      "targetIndex": 723,
      "zoneID": 216
    },
    {
      "name": "Veridical Conflux #02",
      "serverID": 17662676,
      "targetIndex": 724,
      "zoneID": 216
    },
    {
      "name": "Veridical Conflux #03",
      "serverID": 17662677,
      "targetIndex": 725,
      "zoneID": 216
    },
    {
      "name": "Veridical Conflux #04",
      "serverID": 17662678,
      "targetIndex": 726,
      "zoneID": 216
    },
    {
      "name": "Veridical Conflux #05",
      "serverID": 17662679,
      "targetIndex": 727,
      "zoneID": 216
    },
    {
      "name": "Veridical Conflux #06",
      "serverID": 17662680,
      "targetIndex": 728,
      "zoneID": 216
    },
    {
      "name": "Veridical Conflux #07",
      "serverID": 17662681,
      "targetIndex": 729,
      "zoneID": 216
    },
    {
      "name": "Veridical Conflux #08",
      "serverID": 17662682,
      "targetIndex": 730,
      "zoneID": 216
    },
    {
      "name": "MS-01 Martello",
      "serverID": 17662683,
      "targetIndex": 731,
      "zoneID": 216
    },
    {
      "name": "MS-02 Martello",
      "serverID": 17662684,
      "targetIndex": 732,
      "zoneID": 216
    },
    {
      "name": "MS-03 Martello",
      "serverID": 17662685,
      "targetIndex": 733,
      "zoneID": 216
    },
    {
      "name": "MS-04 Martello",
      "serverID": 17662686,
      "targetIndex": 734,
      "zoneID": 216
    },
    {
      "name": "MS-05 Martello",
      "serverID": 17662687,
      "targetIndex": 735,
      "zoneID": 216
    },
    {
      "name": "MS-06 Martello",
      "serverID": 17662688,
      "targetIndex": 736,
      "zoneID": 216
    },
    {
      "name": "MS-07 Martello",
      "serverID": 17662689,
      "targetIndex": 737,
      "zoneID": 216
    },
    {
      "name": "MS-08 Martello",
      "serverID": 17662690,
      "targetIndex": 738,
      "zoneID": 216
    },
    {
      "name": "Bastion Prefect",
      "serverID": 17662691,
      "targetIndex": 739,
      "zoneID": 216
    },
    {
      "name": "BCG Debug Master",
      "serverID": 17662692,
      "targetIndex": 740,
      "zoneID": 216
    },
    {
      "name": "Resistance Sergeant",
      "serverID": 17662693,
      "targetIndex": 741,
      "zoneID": 216
    },
    {
      "name": "Veridical Conflux #00",
      "serverID": 17662694,
      "targetIndex": 742,
      "zoneID": 216
    },
    {
      "name": "Pulse Martello",
      "serverID": 17662695,
      "targetIndex": 743,
      "zoneID": 216
    },
    {
      "name": "Clone Ward",
      "serverID": 17662696,
      "targetIndex": 744,
      "zoneID": 216
    },
    {
      "name": "Clone Ward",
      "serverID": 17662697,
      "targetIndex": 745,
      "zoneID": 216
    },
    {
      "name": "Clone Ward",
      "serverID": 17662698,
      "targetIndex": 746,
      "zoneID": 216
    },
    {
      "name": "Clone Ward",
      "serverID": 17662699,
      "targetIndex": 747,
      "zoneID": 216
    },
    {
      "name": "Clone Ward",
      "serverID": 17662700,
      "targetIndex": 748,
      "zoneID": 216
    },
    {
      "name": "Clone Ward",
      "serverID": 17662701,
      "targetIndex": 749,
      "zoneID": 216
    },
    {
      "name": "Clone Ward",
      "serverID": 17662702,
      "targetIndex": 750,
      "zoneID": 216
    },
    {
      "name": "Fore Trap",
      "serverID": 17662703,
      "targetIndex": 751,
      "zoneID": 216
    },
    {
      "name": "Fore Trap",
      "serverID": 17662704,
      "targetIndex": 752,
      "zoneID": 216
    },
    {
      "name": "Fore Trap",
      "serverID": 17662705,
      "targetIndex": 753,
      "zoneID": 216
    },
    {
      "name": "Rear Trap",
      "serverID": 17662706,
      "targetIndex": 754,
      "zoneID": 216
    },
    {
      "name": "Rear Trap",
      "serverID": 17662707,
      "targetIndex": 755,
      "zoneID": 216
    },
    {
      "name": "Rear Trap",
      "serverID": 17662708,
      "targetIndex": 756,
      "zoneID": 216
    },
    {
      "name": "",
      "serverID": 17662711,
      "targetIndex": 759,
      "zoneID": 216
    },
    {
      "name": "Logging Point",
      "serverID": 17662716,
      "targetIndex": 764,
      "zoneID": 216
    },
    {
      "name": "Logging Point",
      "serverID": 17662717,
      "targetIndex": 765,
      "zoneID": 216
    },
    {
      "name": "Logging Point",
      "serverID": 17662718,
      "targetIndex": 766,
      "zoneID": 216
    },
    {
      "name": "Logging Point",
      "serverID": 17662719,
      "targetIndex": 767,
      "zoneID": 216
    },
    {
      "name": "Logging Point",
      "serverID": 17662720,
      "targetIndex": 768,
      "zoneID": 216
    },
    {
      "name": "Logging Point",
      "serverID": 17662721,
      "targetIndex": 769,
      "zoneID": 216
    },
    {
      "name": "Cavernous Maw",
      "serverID": 17662722,
      "targetIndex": 770,
      "zoneID": 216
    },
    {
      "name": "",
      "serverID": 17662723,
      "targetIndex": 771,
      "zoneID": 216
    },
    {
      "name": "Iron Eater",
      "serverID": 17662724,
      "targetIndex": 772,
      "zoneID": 216
    },
    {
      "name": "Fariel",
      "serverID": 17662725,
      "targetIndex": 773,
      "zoneID": 216
    },
    {
      "name": "Mathurin",
      "serverID": 17662726,
      "targetIndex": 774,
      "zoneID": 216
    },
    {
      "name": "Quasim",
      "serverID": 17662727,
      "targetIndex": 775,
      "zoneID": 216
    },
    {
      "name": "Goraow",
      "serverID": 17662728,
      "targetIndex": 776,
      "zoneID": 216
    },
    {
      "name": "Grassy Mound",
      "serverID": 17662729,
      "targetIndex": 777,
      "zoneID": 216
    },
    {
      "name": "Veit",
      "serverID": 17662730,
      "targetIndex": 778,
      "zoneID": 216
    },
    {
      "name": "Sieglinde",
      "serverID": 17662731,
      "targetIndex": 779,
      "zoneID": 216
    },
    {
      "name": "Yurim",
      "serverID": 17662732,
      "targetIndex": 780,
      "zoneID": 216
    },
    {
      "name": "Jonette",
      "serverID": 17662733,
      "targetIndex": 781,
      "zoneID": 216
    },
    {
      "name": "???",
      "serverID": 17662734,
      "targetIndex": 782,
      "zoneID": 216
    },
    {
      "name": "Yasuji",
      "serverID": 17662735,
      "targetIndex": 783,
      "zoneID": 216
    },
    {
      "name": "Hungry Wolf",
      "serverID": 17662736,
      "targetIndex": 784,
      "zoneID": 216
    },
    {
      "name": "???",
      "serverID": 17662737,
      "targetIndex": 785,
      "zoneID": 216
    },
    {
      "name": "Dilapidated Gate",
      "serverID": 17662738,
      "targetIndex": 786,
      "zoneID": 216
    },
    {
      "name": "Dilapidated Gate",
      "serverID": 17662739,
      "targetIndex": 787,
      "zoneID": 216
    },
    {
      "name": "Dilapidated Gate",
      "serverID": 17662740,
      "targetIndex": 788,
      "zoneID": 216
    },
    {
      "name": "Dilapidated Gate",
      "serverID": 17662741,
      "targetIndex": 789,
      "zoneID": 216
    },
    {
      "name": "Lame Deer",
      "serverID": 17662742,
      "targetIndex": 790,
      "zoneID": 216
    },
    {
      "name": "Ferghus",
      "serverID": 17662743,
      "targetIndex": 791,
      "zoneID": 216
    },
    {
      "name": "Hans",
      "serverID": 17662744,
      "targetIndex": 792,
      "zoneID": 216
    },
    {
      "name": "Kurando",
      "serverID": 17662745,
      "targetIndex": 793,
      "zoneID": 216
    },
    {
      "name": "Big Harvest",
      "serverID": 17662746,
      "targetIndex": 794,
      "zoneID": 216
    },
    {
      "name": "Masis",
      "serverID": 17662747,
      "targetIndex": 795,
      "zoneID": 216
    },
    {
      "name": "Geuselibel",
      "serverID": 17662748,
      "targetIndex": 796,
      "zoneID": 216
    },
    {
      "name": "Zadant",
      "serverID": 17662749,
      "targetIndex": 797,
      "zoneID": 216
    },
    {
      "name": "Bibokk-Molbukk",
      "serverID": 17662750,
      "targetIndex": 798,
      "zoneID": 216
    },
    {
      "name": "Guda",
      "serverID": 17662751,
      "targetIndex": 799,
      "zoneID": 216
    },
    {
      "name": "Izabele",
      "serverID": 17662752,
      "targetIndex": 800,
      "zoneID": 216
    },
    {
      "name": "Ondieulix",
      "serverID": 17662753,
      "targetIndex": 801,
      "zoneID": 216
    },
    {
      "name": "Leporaitceau",
      "serverID": 17662754,
      "targetIndex": 802,
      "zoneID": 216
    },
    {
      "name": "Mengrenaux",
      "serverID": 17662755,
      "targetIndex": 803,
      "zoneID": 216
    },
    {
      "name": "Nicadio",
      "serverID": 17662756,
      "targetIndex": 804,
      "zoneID": 216
    },
    {
      "name": "Amar",
      "serverID": 17662757,
      "targetIndex": 805,
      "zoneID": 216
    },
    {
      "name": "Anguysh",
      "serverID": 17662758,
      "targetIndex": 806,
      "zoneID": 216
    },
    {
      "name": "Tancredi",
      "serverID": 17662759,
      "targetIndex": 807,
      "zoneID": 216
    },
    {
      "name": "",
      "serverID": 17662760,
      "targetIndex": 808,
      "zoneID": 216
    },
    {
      "name": "",
      "serverID": 17662761,
      "targetIndex": 809,
      "zoneID": 216
    },
    {
      "name": "",
      "serverID": 17662762,
      "targetIndex": 810,
      "zoneID": 216
    },
    {
      "name": "",
      "serverID": 17662763,
      "targetIndex": 811,
      "zoneID": 216
    },
    {
      "name": "Repair Trunk",
      "serverID": 17662764,
      "targetIndex": 812,
      "zoneID": 216
    },
    {
      "name": "Repair Trunk",
      "serverID": 17662765,
      "targetIndex": 813,
      "zoneID": 216
    },
    {
      "name": "Repair Trunk",
      "serverID": 17662766,
      "targetIndex": 814,
      "zoneID": 216
    },
    {
      "name": "Repair Trunk",
      "serverID": 17662767,
      "targetIndex": 815,
      "zoneID": 216
    },
    {
      "name": "Repair Trunk",
      "serverID": 17662768,
      "targetIndex": 816,
      "zoneID": 216
    },
    {
      "name": "Repair Trunk",
      "serverID": 17662769,
      "targetIndex": 817,
      "zoneID": 216
    },
    {
      "name": "Repair Trunk",
      "serverID": 17662770,
      "targetIndex": 818,
      "zoneID": 216
    },
    {
      "name": "Repair Trunk",
      "serverID": 17662771,
      "targetIndex": 819,
      "zoneID": 216
    },
    {
      "name": "Repair Trunk",
      "serverID": 17662772,
      "targetIndex": 820,
      "zoneID": 216
    },
    {
      "name": "Repair Trunk",
      "serverID": 17662773,
      "targetIndex": 821,
      "zoneID": 216
    },
    {
      "name": "Event Master",
      "serverID": 17662774,
      "targetIndex": 822,
      "zoneID": 216
    },
    {
      "name": "",
      "serverID": 17662775,
      "targetIndex": 823,
      "zoneID": 216
    },
    {
      "name": "Panta-Putta",
      "serverID": 17662776,
      "targetIndex": 824,
      "zoneID": 216
    },
    {
      "name": "Machine Outfitter",
      "serverID": 17662777,
      "targetIndex": 825,
      "zoneID": 216
    },
    {
      "name": "Resistance Sapper",
      "serverID": 17662778,
      "targetIndex": 826,
      "zoneID": 216
    },
    {
      "name": "Repair Trunk",
      "serverID": 17662779,
      "targetIndex": 827,
      "zoneID": 216
    },
    {
      "name": "Repair Trunk",
      "serverID": 17662780,
      "targetIndex": 828,
      "zoneID": 216
    },
    {
      "name": "Chocobo Tamer",
      "serverID": 17662781,
      "targetIndex": 829,
      "zoneID": 216
    },
    {
      "name": "Chocobo",
      "serverID": 17662782,
      "targetIndex": 830,
      "zoneID": 216
    },
    {
      "name": "Chocobo",
      "serverID": 17662783,
      "targetIndex": 831,
      "zoneID": 216
    },
    {
      "name": "Chocobo",
      "serverID": 17662784,
      "targetIndex": 832,
      "zoneID": 216
    },
    {
      "name": "Repair Trunk",
      "serverID": 17662785,
      "targetIndex": 833,
      "zoneID": 216
    },
    {
      "name": "Repair Trunk",
      "serverID": 17662786,
      "targetIndex": 834,
      "zoneID": 216
    },
    {
      "name": "Moogle",
      "serverID": 17662788,
      "targetIndex": 836,
      "zoneID": 216
    },
    {
      "name": "Moogle",
      "serverID": 17662789,
      "targetIndex": 837,
      "zoneID": 216
    },
    {
      "name": "Moogle",
      "serverID": 17662790,
      "targetIndex": 838,
      "zoneID": 216
    },
    {
      "name": "Moogle",
      "serverID": 17662791,
      "targetIndex": 839,
      "zoneID": 216
    },
    {
      "name": "Moogle",
      "serverID": 17662792,
      "targetIndex": 840,
      "zoneID": 216
    },
    {
      "name": "Moogle",
      "serverID": 17662793,
      "targetIndex": 841,
      "zoneID": 216
    },
    {
      "name": "Moogle",
      "serverID": 17662794,
      "targetIndex": 842,
      "zoneID": 216
    },
    {
      "name": "Moogle",
      "serverID": 17662795,
      "targetIndex": 843,
      "zoneID": 216
    }
  ]
}