[
  {
    "FileID": 42991,
    "Path": "C:\\Program Files (x86)\\PlayOnline\\SquareEnix\\FINAL FANTASY XI\\ROM\\111\\66.DAT"
  },
  {
    "FileID": 42993,
    "Path": "C:\\Program Files (x86)\\PlayOnline\\SquareEnix\\FINAL FANTASY XI\\ROM\\111\\67.DAT"
  },
  {
    "FileID": 42994,
    "Path": "C:\\Program Files (x86)\\PlayOnline\\SquareEnix\\FINAL FANTASY XI\\ROM\\111\\68.DAT"
  },
  {
    "FileID": 43000,
    "Path": "C:\\Program Files (x86)\\PlayOnline\\SquareEnix\\FINAL FANTASY XI\\ROM\\111\\69.DAT"
  },
  {
    "FileID": 43119,
    "Path": "C:\\Program Files (x86)\\PlayOnline\\SquareEnix\\FINAL FANTASY XI\\ROM\\111\\70.DAT"
  },
  {
    "FileID": 43121,
    "Path": "C:\\Program Files (x86)\\PlayOnline\\SquareEnix\\FINAL FANTASY XI\\ROM\\111\\71.DAT"
  },
  {
    "FileID": 43122,
    "Path": "C:\\Program Files (x86)\\PlayOnline\\SquareEnix\\FINAL FANTASY XI\\ROM\\111\\72.DAT"
  },
  {
    "FileID": 43128,
    "Path": "C:\\Program Files (x86)\\PlayOnline\\SquareEnix\\FINAL FANTASY XI\\ROM\\111\\73.DAT"
  },
  {
    "FileID": 43247,
    "Path": "C:\\Program Files (x86)\\PlayOnline\\SquareEnix\\FINAL FANTASY XI\\ROM\\111\\74.DAT"
  },
  {
    "FileID": 43249,
    "Path": "C:\\Program Files (x86)\\PlayOnline\\SquareEnix\\FINAL FANTASY XI\\ROM\\111\\75.DAT"
  },
  {
    "FileID": 43250,
    "Path": "C:\\Program Files (x86)\\PlayOnline\\SquareEnix\\FINAL FANTASY XI\\ROM\\111\\76.DAT"
  },
  {
    "FileID": 43256,
    "Path": "C:\\Program Files (x86)\\PlayOnline\\SquareEnix\\FINAL FANTASY XI\\ROM\\111\\77.DAT"
  },
  {
    "FileID": 43375,
    "Path": "C:\\Program Files (x86)\\PlayOnline\\SquareEnix\\FINAL FANTASY XI\\ROM\\111\\78.DAT"
  },
  {
    "FileID": 43377,
    "Path": "C:\\Program Files (x86)\\PlayOnline\\SquareEnix\\FINAL FANTASY XI\\ROM\\111\\79.DAT"
  },
  {
    "FileID": 43378,
    "Path": "C:\\Program Files (x86)\\PlayOnline\\SquareEnix\\FINAL FANTASY XI\\ROM\\111\\80.DAT"
  },
  {
    "FileID": 43384,
    "Path": "C:\\Program Files (x86)\\PlayOnline\\SquareEnix\\FINAL FANTASY XI\\ROM\\111\\81.DAT"
  },
  {
    "FileID": 43503,
    "Path": "C:\\Program Files (x86)\\PlayOnline\\SquareEnix\\FINAL FANTASY XI\\ROM\\111\\82.DAT"
  },
  {
    "FileID": 43505,
    "Path": "C:\\Program Files (x86)\\PlayOnline\\SquareEnix\\FINAL FANTASY XI\\ROM\\111\\83.DAT"
  },
  {
    "FileID": 43506,
    "Path": "C:\\Program Files (x86)\\PlayOnline\\SquareEnix\\FINAL FANTASY XI\\ROM\\111\\84.DAT"
  },
  {
    "FileID": 43512,
    "Path": "C:\\Program Files (x86)\\PlayOnline\\SquareEnix\\FINAL FANTASY XI\\ROM\\111\\85.DAT"
  },
  {
    "FileID": 43631,
    "Path": "C:\\Program Files (x86)\\PlayOnline\\SquareEnix\\FINAL FANTASY XI\\ROM\\111\\86.DAT"
  },
  {
    "FileID": 43633,
    "Path": "C:\\Program Files (x86)\\PlayOnline\\SquareEnix\\FINAL FANTASY XI\\ROM\\111\\87.DAT"
  },
  {
    "FileID": 43634,
    "Path": "C:\\Program Files (x86)\\PlayOnline\\SquareEnix\\FINAL FANTASY XI\\ROM\\111\\88.DAT"
  },
  {
    "FileID": 43640,
    "Path": "C:\\Program Files (x86)\\PlayOnline\\SquareEnix\\FINAL FANTASY XI\\ROM\\111\\89.DAT"
  },
  {
    "FileID": 61550,
    "Path": "C:\\Program Files (x86)\\PlayOnline\\SquareEnix\\FINAL FANTASY XI\\ROM\\204\\27.DAT"
  },
  {
    "FileID": 61554,
    "Path": "C:\\Program Files (x86)\\PlayOnline\\SquareEnix\\FINAL FANTASY XI\\ROM\\256\\24.DAT"
  },
  {
    "FileID": 61570,
    "Path": "C:\\Program Files (x86)\\PlayOnline\\SquareEnix\\FINAL FANTASY XI\\ROM\\256\\25.DAT"
  },
  {
    "FileID": 61586,
    "Path": "C:\\Program Files (x86)\\PlayOnline\\SquareEnix\\FINAL FANTASY XI\\ROM\\256\\26.DAT"
  },
  {
    "FileID": 34883,
    "Path": "C:\\Program Files (x86)\\PlayOnline\\SquareEnix\\FINAL FANTASY XI\\ROM\\308\\101.DAT"
  },
  {
    "FileID": 35139,
    "Path": "C:\\Program Files (x86)\\PlayOnline\\SquareEnix\\FINAL FANTASY XI\\ROM\\308\\102.DAT"
  },
  {
    "FileID": 35395,
    "Path": "C:\\Program Files (x86)\\PlayOnline\\SquareEnix\\FINAL FANTASY XI\\ROM\\308\\103.DAT"
  },
  {
    "FileID": 70688,
    "Path": "C:\\Program Files (x86)\\PlayOnline\\SquareEnix\\FINAL FANTASY XI\\ROM\\320\\76.DAT"
  },
  {
    "FileID": 16159,
    "Path": "C:\\Program Files (x86)\\PlayOnline\\SquareEnix\\FINAL FANTASY XI\\ROM\\41\\100.DAT"
  },
  {
    "FileID": 16160,
    "Path": "C:\\Program Files (x86)\\PlayOnline\\SquareEnix\\FINAL FANTASY XI\\ROM\\41\\101.DAT"
  },
  {
    "FileID": 16161,
    "Path": "C:\\Program Files (x86)\\PlayOnline\\SquareEnix\\FINAL FANTASY XI\\ROM\\41\\102.DAT"
  },
  {
    "FileID": 16162,
    "Path": "C:\\Program Files (x86)\\PlayOnline\\SquareEnix\\FINAL FANTASY XI\\ROM\\41\\103.DAT"
  },
  {
    "FileID": 16280,
    "Path": "C:\\Program Files (x86)\\PlayOnline\\SquareEnix\\FINAL FANTASY XI\\ROM\\41\\104.DAT"
  },
  {
    "FileID": 16281,
    "Path": "C:\\Program Files (x86)\\PlayOnline\\SquareEnix\\FINAL FANTASY XI\\ROM\\41\\105.DAT"
  },
  {
    "FileID": 16282,
    "Path": "C:\\Program Files (x86)\\PlayOnline\\SquareEnix\\FINAL FANTASY XI\\ROM\\41\\106.DAT"
  },
  {
    "FileID": 16284,
    "Path": "C:\\Program Files (x86)\\PlayOnline\\SquareEnix\\FINAL FANTASY XI\\ROM\\41\\107.DAT"
  },
  {
    "FileID": 16285,
    "Path": "C:\\Program Files (x86)\\PlayOnline\\SquareEnix\\FINAL FANTASY XI\\ROM\\41\\108.DAT"
  },
  {
    "FileID": 16286,
    "Path": "C:\\Program Files (x86)\\PlayOnline\\SquareEnix\\FINAL FANTASY XI\\ROM\\41\\109.DAT"
  },
  {
    "FileID": 16287,
    "Path": "C:\\Program Files (x86)\\PlayOnline\\SquareEnix\\FINAL FANTASY XI\\ROM\\41\\110.DAT"
  },
  {
    "FileID": 16288,
    "Path": "C:\\Program Files (x86)\\PlayOnline\\SquareEnix\\FINAL FANTASY XI\\ROM\\41\\111.DAT"
  },
  {
    "FileID": 16289,
    "Path": "C:\\Program Files (x86)\\PlayOnline\\SquareEnix\\FINAL FANTASY XI\\ROM\\41\\112.DAT"
  },
  {
    "FileID": 16290,
    "Path": "C:\\Program Files (x86)\\PlayOnline\\SquareEnix\\FINAL FANTASY XI\\ROM\\41\\113.DAT"
  },
  {
    "FileID": 16024,
    "Path": "C:\\Program Files (x86)\\PlayOnline\\SquareEnix\\FINAL FANTASY XI\\ROM\\41\\84.DAT"
  },
  {
    "FileID": 16025,
    "Path": "C:\\Program Files (x86)\\PlayOnline\\SquareEnix\\FINAL FANTASY XI\\ROM\\41\\85.DAT"
  },
  {
    "FileID": 16026,
    "Path": "C:\\Program Files (x86)\\PlayOnline\\SquareEnix\\FINAL FANTASY XI\\ROM\\41\\86.DAT"
  },
  {
    "FileID": 16028,
    "Path": "C:\\Program Files (x86)\\PlayOnline\\SquareEnix\\FINAL FANTASY XI\\ROM\\41\\87.DAT"
  },
  {
    "FileID": 16029,
    "Path": "C:\\Program Files (x86)\\PlayOnline\\SquareEnix\\FINAL FANTASY XI\\ROM\\41\\88.DAT"
  },
  {
    "FileID": 16030,
    "Path": "C:\\Program Files (x86)\\PlayOnline\\SquareEnix\\FINAL FANTASY XI\\ROM\\41\\89.DAT"
  },
  {
    "FileID": 16031,
    "Path": "C:\\Program Files (x86)\\PlayOnline\\SquareEnix\\FINAL FANTASY XI\\ROM\\41\\90.DAT"
  },
  {
    "FileID": 16032,
    "Path": "C:\\Program Files (x86)\\PlayOnline\\SquareEnix\\FINAL FANTASY XI\\ROM\\41\\91.DAT"
  },
  {
    "FileID": 16033,
    "Path": "C:\\Program Files (x86)\\PlayOnline\\SquareEnix\\FINAL FANTASY XI\\ROM\\41\\92.DAT"
  },
  {
    "FileID": 16034,
    "Path": "C:\\Program Files (x86)\\PlayOnline\\SquareEnix\\FINAL FANTASY XI\\ROM\\41\\93.DAT"
  },
  {
    "FileID": 16152,
    "Path": "C:\\Program Files (x86)\\PlayOnline\\SquareEnix\\FINAL FANTASY XI\\ROM\\41\\94.DAT"
  },
  {
    "FileID": 16153,
    "Path": "C:\\Program Files (x86)\\PlayOnline\\SquareEnix\\FINAL FANTASY XI\\ROM\\41\\95.DAT"
  },
  {
    "FileID": 16154,
    "Path": "C:\\Program Files (x86)\\PlayOnline\\SquareEnix\\FINAL FANTASY XI\\ROM\\41\\96.DAT"
  },
  {
    "FileID": 16156,
    "Path": "C:\\Program Files (x86)\\PlayOnline\\SquareEnix\\FINAL FANTASY XI\\ROM\\41\\97.DAT"
  },
  {
    "FileID": 16157,
    "Path": "C:\\Program Files (x86)\\PlayOnline\\SquareEnix\\FINAL FANTASY XI\\ROM\\41\\98.DAT"
  },
  {
    "FileID": 16158,
    "Path": "C:\\Program Files (x86)\\PlayOnline\\SquareEnix\\FINAL FANTASY XI\\ROM\\41\\99.DAT"
  },
  {
    "FileID": 29940,
    "Path": "C:\\Program Files (x86)\\PlayOnline\\SquareEnix\\FINAL FANTASY XI\\ROM\\61\\63.DAT"
  },
  {
    "FileID": 29941,
    "Path": "C:\\Program Files (x86)\\PlayOnline\\SquareEnix\\FINAL FANTASY XI\\ROM\\61\\64.DAT"
  },
  {
    "FileID": 34948,
    "Path": "C:\\Program Files (x86)\\PlayOnline\\SquareEnix\\FINAL FANTASY XI\\ROM\\80\\110.DAT"
  },
  {
    "FileID": 35204,
    "Path": "C:\\Program Files (x86)\\PlayOnline\\SquareEnix\\FINAL FANTASY XI\\ROM\\81\\67.DAT"
  },
  {
    "FileID": 35460,
    "Path": "C:\\Program Files (x86)\\PlayOnline\\SquareEnix\\FINAL FANTASY XI\\ROM\\82\\24.DAT"
  },
  {
    "FileID": 16027,
    "Path": "C:\\Program Files (x86)\\PlayOnline\\SquareEnix\\FINAL FANTASY XI\\ROM\\98\\117.DAT"
  },
  {
    "FileID": 16155,
    "Path": "C:\\Program Files (x86)\\PlayOnline\\SquareEnix\\FINAL FANTASY XI\\ROM\\98\\118.DAT"
  },
  {
    "FileID": 16283,
    "Path": "C:\\Program Files (x86)\\PlayOnline\\SquareEnix\\FINAL FANTASY XI\\ROM\\98\\119.DAT"
  }
]